<?xml version="1.0" encoding="utf-8"?>
<Return xmlns="http://www.irs.gov/efile" xmlns:xsi="http://www.w3.org/2001/XMLSchema-instance" returnVersion="2021v4.1" xsi:schemaLocation="http://www.irs.gov/efile">
  <ReturnHeader binaryAttachmentCnt="0">
    <ReturnTs>2023-05-02T01:33:58-07:00</ReturnTs>
    <TaxPeriodEndDt>2022-06-30</TaxPeriodEndDt>
    <PreparerFirmGrp>
      <PreparerFirmEIN>270741376</PreparerFirmEIN>
      <PreparerFirmName>
        <BusinessNameLine1Txt>HARSHWAL &amp; COMPANY LLP</BusinessNameLine1Txt>
      </PreparerFirmName>
      <PreparerUSAddress>
        <AddressLine1Txt>7677 OAKPORT ST STE 460</AddressLine1Txt>
        <CityNm>OAKLAND</CityNm>
        <StateAbbreviationCd>CA</StateAbbreviationCd>
        <ZIPCd>94621</ZIPCd>
      </PreparerUSAddress>
    </PreparerFirmGrp>
    <ReturnTypeCd>990</ReturnTypeCd>
    <TaxPeriodBeginDt>2021-07-01</TaxPeriodBeginDt>
    <Filer>
      <EIN>510163201</EIN>
      <BusinessName>
        <BusinessNameLine1Txt>ACCESS REPRODUCTIVE JUSTICE</BusinessNameLine1Txt>
      </BusinessName>
      <BusinessNameControlTxt>ACCE</BusinessNameControlTxt>
      <PhoneNum>5109230729</PhoneNum>
      <USAddress>
        <AddressLine1Txt>2323 BROADWAY</AddressLine1Txt>
        <CityNm>OAKLAND</CityNm>
        <StateAbbreviationCd>CA</StateAbbreviationCd>
        <ZIPCd>94612</ZIPCd>
      </USAddress>
    </Filer>
    <BusinessOfficerGrp>
      <PersonNm>Jessica Gil</PersonNm>
      <PersonTitleTxt>Executive Director</PersonTitleTxt>
      <SignatureDt>2023-05-02</SignatureDt>
      <DiscussWithPaidPreparerInd>true</DiscussWithPaidPreparerInd>
    </BusinessOfficerGrp>
    <SigningOfficerGrp>
      <PersonFullName>
        <PersonFirstNm>Jessica</PersonFirstNm>
        <PersonLastNm>Gil</PersonLastNm>
      </PersonFullName>
      <SSN>999009999</SSN>
    </SigningOfficerGrp>
    <PreparerPersonGrp>
      <PreparerPersonNm>Sanwar Harshwal CPA</PreparerPersonNm>
      <PTIN>P01249746</PTIN>
      <PhoneNum>5104525051</PhoneNum>
      <SelfEmployedInd>X</SelfEmployedInd>
    </PreparerPersonGrp>
    <AdditionalFilerInformation>
      <TrustedCustomerGrp>
        <TrustedCustomerCd>2</TrustedCustomerCd>
        <AuthenticationAssuranceLevelCd>AAL1</AuthenticationAssuranceLevelCd>
        <IdentityAssuranceLevelCd>IAL1</IdentityAssuranceLevelCd>
        <FederatedAssuranceLevelCd>FAL1</FederatedAssuranceLevelCd>
      </TrustedCustomerGrp>
    </AdditionalFilerInformation>
    <TaxYr>2021</TaxYr>
    <BuildTS>2023-04-26 12:10:37Z</BuildTS>
  </ReturnHeader>
  <ReturnData documentCnt="6">
    <IRS990 documentId="IRS990" referenceDocumentId="IRS990ScheduleO" softwareId="21013475" softwareVersionNum="2021v4.1">
      <AddressChangeInd>X</AddressChangeInd>
      <PrincipalOfficerNm>Jessica Gil</PrincipalOfficerNm>
      <USAddress>
        <AddressLine1Txt>2323 BROADWAY</AddressLine1Txt>
        <CityNm>OAKLAND</CityNm>
        <StateAbbreviationCd>CA</StateAbbreviationCd>
        <ZIPCd>94612</ZIPCd>
      </USAddress>
      <GrossReceiptsAmt>1111992</GrossReceiptsAmt>
      <GroupReturnForAffiliatesInd>false</GroupReturnForAffiliatesInd>
      <Organization501c3Ind>X</Organization501c3Ind>
      <WebsiteAddressTxt>https://accessrj.org</WebsiteAddressTxt>
      <TypeOfOrganizationCorpInd>X</TypeOfOrganizationCorpInd>
      <FormationYr>1975</FormationYr>
      <LegalDomicileStateCd>CA</LegalDomicileStateCd>
      <ActivityOrMissionDesc>The purpose of ACCESS REPRODUCTIVE JUSTICE is to remove barriers to sexual and reproductive health care and build the power of Californians to demand health, justice, and dignity.</ActivityOrMissionDesc>
      <VotingMembersGoverningBodyCnt>12</VotingMembersGoverningBodyCnt>
      <VotingMembersIndependentCnt>0</VotingMembersIndependentCnt>
      <TotalEmployeeCnt>6</TotalEmployeeCnt>
      <TotalVolunteersCnt>350</TotalVolunteersCnt>
      <TotalGrossUBIAmt>0</TotalGrossUBIAmt>
      <PYContributionsGrantsAmt>713042</PYContributionsGrantsAmt>
      <CYContributionsGrantsAmt>1046560</CYContributionsGrantsAmt>
      <CYProgramServiceRevenueAmt>0</CYProgramServiceRevenueAmt>
      <PYInvestmentIncomeAmt>1017</PYInvestmentIncomeAmt>
      <CYInvestmentIncomeAmt>685</CYInvestmentIncomeAmt>
      <PYOtherRevenueAmt>23530</PYOtherRevenueAmt>
      <CYOtherRevenueAmt>63865</CYOtherRevenueAmt>
      <PYTotalRevenueAmt>737589</PYTotalRevenueAmt>
      <CYTotalRevenueAmt>1111110</CYTotalRevenueAmt>
      <CYGrantsAndSimilarPaidAmt>27500</CYGrantsAndSimilarPaidAmt>
      <CYBenefitsPaidToMembersAmt>0</CYBenefitsPaidToMembersAmt>
      <PYSalariesCompEmpBnftPaidAmt>275036</PYSalariesCompEmpBnftPaidAmt>
      <CYSalariesCompEmpBnftPaidAmt>466322</CYSalariesCompEmpBnftPaidAmt>
      <CYTotalProfFndrsngExpnsAmt>0</CYTotalProfFndrsngExpnsAmt>
      <CYTotalFundraisingExpenseAmt>76543</CYTotalFundraisingExpenseAmt>
      <PYOtherExpensesAmt>277942</PYOtherExpensesAmt>
      <CYOtherExpensesAmt>318892</CYOtherExpensesAmt>
      <PYTotalExpensesAmt>552978</PYTotalExpensesAmt>
      <CYTotalExpensesAmt>812714</CYTotalExpensesAmt>
      <PYRevenuesLessExpensesAmt>184611</PYRevenuesLessExpensesAmt>
      <CYRevenuesLessExpensesAmt>298396</CYRevenuesLessExpensesAmt>
      <TotalAssetsBOYAmt>970723</TotalAssetsBOYAmt>
      <TotalAssetsEOYAmt>1288203</TotalAssetsEOYAmt>
      <TotalLiabilitiesBOYAmt>19582</TotalLiabilitiesBOYAmt>
      <TotalLiabilitiesEOYAmt>40504</TotalLiabilitiesEOYAmt>
      <NetAssetsOrFundBalancesBOYAmt>951141</NetAssetsOrFundBalancesBOYAmt>
      <NetAssetsOrFundBalancesEOYAmt>1247699</NetAssetsOrFundBalancesEOYAmt>
      <MissionDesc>The purpose of ACCESS REPRODUCTIVE JUSTICE is to remove barriers to sexual and reproductive health care and build the power of Californians to demand health, justice, and dignity.</MissionDesc>
      <SignificantNewProgramSrvcInd>false</SignificantNewProgramSrvcInd>
      <SignificantChangeInd>false</SignificantChangeInd>
      <ExpenseAmt>278734</ExpenseAmt>
      <Desc>Healthline - 671 callers supported on the Healthline with $109,235.88 Justice in Action funds.</Desc>
      <ProgSrvcAccomActy2Grp>
        <ExpenseAmt>153898</ExpenseAmt>
        <Desc>Volunteer Engagement - Volunteer Training Application, Vetting Process, and Curriculum Developed; 5+ Volunteer Trainings held to train Practical Support Volunteers.</Desc>
      </ProgSrvcAccomActy2Grp>
      <ProgSrvcAccomActy3Grp>
        <ExpenseAmt>102599</ExpenseAmt>
        <Desc>Policy Advocacy - Org participation on the Steering Committee of the Future of Abortion Council, including shepherding a 15 bill package through the legislative process and advocating for $200M in state funding in the Governor's Budget to support abortion access.</Desc>
      </ProgSrvcAccomActy3Grp>
      <TotalProgramServiceExpensesAmt>535231</TotalProgramServiceExpensesAmt>
      <DescribedInSection501c3Ind referenceDocumentId="IRS990ScheduleA">true</DescribedInSection501c3Ind>
      <ScheduleBRequiredInd referenceDocumentId="IRS990ScheduleB">true</ScheduleBRequiredInd>
      <PoliticalCampaignActyInd>false</PoliticalCampaignActyInd>
      <LobbyingActivitiesInd>false</LobbyingActivitiesInd>
      <SubjectToProxyTaxInd>false</SubjectToProxyTaxInd>
      <DonorAdvisedFundInd referenceDocumentId="IRS990ScheduleD">false</DonorAdvisedFundInd>
      <ConservationEasementsInd referenceDocumentId="IRS990ScheduleD">false</ConservationEasementsInd>
      <CollectionsOfArtInd referenceDocumentId="IRS990ScheduleD">false</CollectionsOfArtInd>
      <CreditCounselingInd referenceDocumentId="IRS990ScheduleD">false</CreditCounselingInd>
      <DonorRstrOrQuasiEndowmentsInd referenceDocumentId="IRS990ScheduleD">false</DonorRstrOrQuasiEndowmentsInd>
      <ReportLandBuildingEquipmentInd referenceDocumentId="IRS990ScheduleD">true</ReportLandBuildingEquipmentInd>
      <ReportInvestmentsOtherSecInd referenceDocumentId="IRS990ScheduleD">false</ReportInvestmentsOtherSecInd>
      <ReportProgramRelatedInvstInd referenceDocumentId="IRS990ScheduleD">false</ReportProgramRelatedInvstInd>
      <ReportOtherAssetsInd referenceDocumentId="IRS990ScheduleD">false</ReportOtherAssetsInd>
      <ReportOtherLiabilitiesInd referenceDocumentId="IRS990ScheduleD">true</ReportOtherLiabilitiesInd>
      <IncludeFIN48FootnoteInd referenceDocumentId="IRS990ScheduleD">false</IncludeFIN48FootnoteInd>
      <IndependentAuditFinclStmtInd referenceDocumentId="IRS990ScheduleD">false</IndependentAuditFinclStmtInd>
      <ConsolidatedAuditFinclStmtInd referenceDocumentId="IRS990ScheduleD">false</ConsolidatedAuditFinclStmtInd>
      <SchoolOperatingInd>false</SchoolOperatingInd>
      <ForeignOfficeInd>false</ForeignOfficeInd>
      <ForeignActivitiesInd>false</ForeignActivitiesInd>
      <MoreThan5000KToOrgInd>false</MoreThan5000KToOrgInd>
      <MoreThan5000KToIndividualsInd>false</MoreThan5000KToIndividualsInd>
      <ProfessionalFundraisingInd referenceDocumentId="IRS990ScheduleG">false</ProfessionalFundraisingInd>
      <FundraisingActivitiesInd referenceDocumentId="IRS990ScheduleG">true</FundraisingActivitiesInd>
      <GamingActivitiesInd referenceDocumentId="IRS990ScheduleG">false</GamingActivitiesInd>
      <OperateHospitalInd>false</OperateHospitalInd>
      <GrantsToOrganizationsInd>false</GrantsToOrganizationsInd>
      <GrantsToIndividualsInd>false</GrantsToIndividualsInd>
      <ScheduleJRequiredInd>false</ScheduleJRequiredInd>
      <TaxExemptBondsInd>false</TaxExemptBondsInd>
      <EngagedInExcessBenefitTransInd>false</EngagedInExcessBenefitTransInd>
      <PYExcessBenefitTransInd>false</PYExcessBenefitTransInd>
      <LoanOutstandingInd>false</LoanOutstandingInd>
      <GrantToRelatedPersonInd>false</GrantToRelatedPersonInd>
      <BusinessRlnWithOrgMemInd>false</BusinessRlnWithOrgMemInd>
      <BusinessRlnWithFamMemInd>false</BusinessRlnWithFamMemInd>
      <BusinessRlnWith35CtrlEntInd>false</BusinessRlnWith35CtrlEntInd>
      <DeductibleNonCashContriInd>false</DeductibleNonCashContriInd>
      <DeductibleArtContributionInd>false</DeductibleArtContributionInd>
      <TerminateOperationsInd>false</TerminateOperationsInd>
      <PartialLiquidationInd>false</PartialLiquidationInd>
      <DisregardedEntityInd>false</DisregardedEntityInd>
      <RelatedEntityInd>false</RelatedEntityInd>
      <RelatedOrganizationCtrlEntInd>false</RelatedOrganizationCtrlEntInd>
      <TrnsfrExmptNonChrtblRltdOrgInd>false</TrnsfrExmptNonChrtblRltdOrgInd>
      <ActivitiesConductedPrtshpInd>false</ActivitiesConductedPrtshpInd>
      <ScheduleORequiredInd>true</ScheduleORequiredInd>
      <IRPDocumentCnt>6</IRPDocumentCnt>
      <IRPDocumentW2GCnt>0</IRPDocumentW2GCnt>
      <BackupWthldComplianceInd>true</BackupWthldComplianceInd>
      <EmployeeCnt>6</EmployeeCnt>
      <EmploymentTaxReturnsFiledInd>true</EmploymentTaxReturnsFiledInd>
      <UnrelatedBusIncmOverLimitInd>false</UnrelatedBusIncmOverLimitInd>
      <ForeignFinancialAccountInd>false</ForeignFinancialAccountInd>
      <ProhibitedTaxShelterTransInd>false</ProhibitedTaxShelterTransInd>
      <TaxablePartyNotificationInd>false</TaxablePartyNotificationInd>
      <NondeductibleContributionsInd>false</NondeductibleContributionsInd>
      <QuidProQuoContributionsInd>false</QuidProQuoContributionsInd>
      <Form8282PropertyDisposedOfInd>false</Form8282PropertyDisposedOfInd>
      <Form8282FiledCnt>0</Form8282FiledCnt>
      <RcvFndsToPayPrsnlBnftCntrctInd>false</RcvFndsToPayPrsnlBnftCntrctInd>
      <PayPremiumsPrsnlBnftCntrctInd>false</PayPremiumsPrsnlBnftCntrctInd>
      <Form8899Filedind>false</Form8899Filedind>
      <Form1098CFiledInd>false</Form1098CFiledInd>
      <IndoorTanningServicesInd>false</IndoorTanningServicesInd>
      <SubjToTaxRmnrtnExPrchtPymtInd>false</SubjToTaxRmnrtnExPrchtPymtInd>
      <SubjectToExcsTaxNetInvstIncInd>false</SubjectToExcsTaxNetInvstIncInd>
      <InfoInScheduleOPartVIInd>X</InfoInScheduleOPartVIInd>
      <GoverningBodyVotingMembersCnt>12</GoverningBodyVotingMembersCnt>
      <IndependentVotingMemberCnt>0</IndependentVotingMemberCnt>
      <FamilyOrBusinessRlnInd>false</FamilyOrBusinessRlnInd>
      <DelegationOfMgmtDutiesInd>false</DelegationOfMgmtDutiesInd>
      <ChangeToOrgDocumentsInd>false</ChangeToOrgDocumentsInd>
      <MaterialDiversionOrMisuseInd>false</MaterialDiversionOrMisuseInd>
      <MembersOrStockholdersInd>false</MembersOrStockholdersInd>
      <ElectionOfBoardMembersInd>false</ElectionOfBoardMembersInd>
      <DecisionsSubjectToApprovaInd>false</DecisionsSubjectToApprovaInd>
      <MinutesOfGoverningBodyInd>true</MinutesOfGoverningBodyInd>
      <MinutesOfCommitteesInd>true</MinutesOfCommitteesInd>
      <OfficerMailingAddressInd>false</OfficerMailingAddressInd>
      <LocalChaptersInd>false</LocalChaptersInd>
      <Form990ProvidedToGvrnBodyInd>true</Form990ProvidedToGvrnBodyInd>
      <ConflictOfInterestPolicyInd>true</ConflictOfInterestPolicyInd>
      <AnnualDisclosureCoveredPrsnInd>true</AnnualDisclosureCoveredPrsnInd>
      <RegularMonitoringEnfrcInd>true</RegularMonitoringEnfrcInd>
      <WhistleblowerPolicyInd>true</WhistleblowerPolicyInd>
      <DocumentRetentionPolicyInd>true</DocumentRetentionPolicyInd>
      <CompensationProcessCEOInd>true</CompensationProcessCEOInd>
      <CompensationProcessOtherInd>false</CompensationProcessOtherInd>
      <InvestmentInJointVentureInd>false</InvestmentInJointVentureInd>
      <StatesWhereCopyOfReturnIsFldCd>CA</StatesWhereCopyOfReturnIsFldCd>
      <UponRequestInd>X</UponRequestInd>
      <BooksInCareOfDetail>
        <PersonNm>ACCESS REPRODUCTIVE JUSTICE</PersonNm>
        <PhoneNum>5109230729</PhoneNum>
        <USAddress>
          <AddressLine1Txt>2323 BROADWAY</AddressLine1Txt>
          <CityNm>OAKLAND</CityNm>
          <StateAbbreviationCd>CA</StateAbbreviationCd>
          <ZIPCd>94612</ZIPCd>
        </USAddress>
      </BooksInCareOfDetail>
      <Form990PartVIISectionAGrp>
        <PersonNm>Jessica Gil</PersonNm>
        <TitleTxt>Executive Dir.</TitleTxt>
        <AverageHoursPerWeekRt>40.00</AverageHoursPerWeekRt>
        <AverageHoursPerWeekRltdOrgRt>0.00</AverageHoursPerWeekRltdOrgRt>
        <OfficerInd>X</OfficerInd>
        <ReportableCompFromOrgAmt>94665</ReportableCompFromOrgAmt>
        <ReportableCompFromRltdOrgAmt>0</ReportableCompFromRltdOrgAmt>
        <OtherCompensationAmt>0</OtherCompensationAmt>
      </Form990PartVIISectionAGrp>
      <Form990PartVIISectionAGrp>
        <PersonNm>Erendira Pineda</PersonNm>
        <TitleTxt>Co Chairman</TitleTxt>
        <AverageHoursPerWeekRt>2.00</AverageHoursPerWeekRt>
        <AverageHoursPerWeekRltdOrgRt>0.00</AverageHoursPerWeekRltdOrgRt>
        <IndividualTrusteeOrDirectorInd>X</IndividualTrusteeOrDirectorInd>
        <OfficerInd>X</OfficerInd>
        <ReportableCompFromOrgAmt>0</ReportableCompFromOrgAmt>
        <ReportableCompFromRltdOrgAmt>0</ReportableCompFromRltdOrgAmt>
        <OtherCompensationAmt>0</OtherCompensationAmt>
      </Form990PartVIISectionAGrp>
      <Form990PartVIISectionAGrp>
        <PersonNm>Lauren Chiharu Ahrum Shinagawa</PersonNm>
        <TitleTxt>Co Chairman</TitleTxt>
        <AverageHoursPerWeekRt>2.00</AverageHoursPerWeekRt>
        <AverageHoursPerWeekRltdOrgRt>0.00</AverageHoursPerWeekRltdOrgRt>
        <IndividualTrusteeOrDirectorInd>X</IndividualTrusteeOrDirectorInd>
        <OfficerInd>X</OfficerInd>
        <ReportableCompFromOrgAmt>0</ReportableCompFromOrgAmt>
        <ReportableCompFromRltdOrgAmt>0</ReportableCompFromRltdOrgAmt>
        <OtherCompensationAmt>0</OtherCompensationAmt>
      </Form990PartVIISectionAGrp>
      <Form990PartVIISectionAGrp>
        <PersonNm>Jennifer Keely Tongate</PersonNm>
        <TitleTxt>Treasurer</TitleTxt>
        <AverageHoursPerWeekRt>2.00</AverageHoursPerWeekRt>
        <AverageHoursPerWeekRltdOrgRt>0.00</AverageHoursPerWeekRltdOrgRt>
        <IndividualTrusteeOrDirectorInd>X</IndividualTrusteeOrDirectorInd>
        <OfficerInd>X</OfficerInd>
        <ReportableCompFromOrgAmt>0</ReportableCompFromOrgAmt>
        <ReportableCompFromRltdOrgAmt>0</ReportableCompFromRltdOrgAmt>
        <OtherCompensationAmt>0</OtherCompensationAmt>
      </Form990PartVIISectionAGrp>
      <Form990PartVIISectionAGrp>
        <PersonNm>Daisy Orellana</PersonNm>
        <TitleTxt>Secretary</TitleTxt>
        <AverageHoursPerWeekRt>2.00</AverageHoursPerWeekRt>
        <AverageHoursPerWeekRltdOrgRt>0.00</AverageHoursPerWeekRltdOrgRt>
        <IndividualTrusteeOrDirectorInd>X</IndividualTrusteeOrDirectorInd>
        <OfficerInd>X</OfficerInd>
        <ReportableCompFromOrgAmt>0</ReportableCompFromOrgAmt>
        <ReportableCompFromRltdOrgAmt>0</ReportableCompFromRltdOrgAmt>
        <OtherCompensationAmt>0</OtherCompensationAmt>
      </Form990PartVIISectionAGrp>
      <Form990PartVIISectionAGrp>
        <PersonNm>Cynthia Gutierrez</PersonNm>
        <TitleTxt>Board Member</TitleTxt>
        <AverageHoursPerWeekRt>2.00</AverageHoursPerWeekRt>
        <AverageHoursPerWeekRltdOrgRt>0.00</AverageHoursPerWeekRltdOrgRt>
        <IndividualTrusteeOrDirectorInd>X</IndividualTrusteeOrDirectorInd>
        <ReportableCompFromOrgAmt>0</ReportableCompFromOrgAmt>
        <ReportableCompFromRltdOrgAmt>0</ReportableCompFromRltdOrgAmt>
        <OtherCompensationAmt>0</OtherCompensationAmt>
      </Form990PartVIISectionAGrp>
      <Form990PartVIISectionAGrp>
        <PersonNm>Lisa Matsubara</PersonNm>
        <TitleTxt>Board Member</TitleTxt>
        <AverageHoursPerWeekRt>2.00</AverageHoursPerWeekRt>
        <AverageHoursPerWeekRltdOrgRt>0.00</AverageHoursPerWeekRltdOrgRt>
        <IndividualTrusteeOrDirectorInd>X</IndividualTrusteeOrDirectorInd>
        <ReportableCompFromOrgAmt>0</ReportableCompFromOrgAmt>
        <ReportableCompFromRltdOrgAmt>0</ReportableCompFromRltdOrgAmt>
        <OtherCompensationAmt>0</OtherCompensationAmt>
      </Form990PartVIISectionAGrp>
      <Form990PartVIISectionAGrp>
        <PersonNm>Sonja Goetsch-Avila</PersonNm>
        <TitleTxt>Board Member</TitleTxt>
        <AverageHoursPerWeekRt>2.00</AverageHoursPerWeekRt>
        <AverageHoursPerWeekRltdOrgRt>0.00</AverageHoursPerWeekRltdOrgRt>
        <IndividualTrusteeOrDirectorInd>X</IndividualTrusteeOrDirectorInd>
        <ReportableCompFromOrgAmt>0</ReportableCompFromOrgAmt>
        <ReportableCompFromRltdOrgAmt>0</ReportableCompFromRltdOrgAmt>
        <OtherCompensationAmt>0</OtherCompensationAmt>
      </Form990PartVIISectionAGrp>
      <Form990PartVIISectionAGrp>
        <PersonNm>Sylvia Castillo</PersonNm>
        <TitleTxt>Board Member</TitleTxt>
        <AverageHoursPerWeekRt>2.00</AverageHoursPerWeekRt>
        <AverageHoursPerWeekRltdOrgRt>0.00</AverageHoursPerWeekRltdOrgRt>
        <IndividualTrusteeOrDirectorInd>X</IndividualTrusteeOrDirectorInd>
        <ReportableCompFromOrgAmt>0</ReportableCompFromOrgAmt>
        <ReportableCompFromRltdOrgAmt>0</ReportableCompFromRltdOrgAmt>
        <OtherCompensationAmt>0</OtherCompensationAmt>
      </Form990PartVIISectionAGrp>
      <Form990PartVIISectionAGrp>
        <PersonNm>Mary Durden</PersonNm>
        <TitleTxt>Board Membr</TitleTxt>
        <AverageHoursPerWeekRt>2.00</AverageHoursPerWeekRt>
        <AverageHoursPerWeekRltdOrgRt>0.00</AverageHoursPerWeekRltdOrgRt>
        <IndividualTrusteeOrDirectorInd>X</IndividualTrusteeOrDirectorInd>
        <ReportableCompFromOrgAmt>0</ReportableCompFromOrgAmt>
        <ReportableCompFromRltdOrgAmt>0</ReportableCompFromRltdOrgAmt>
        <OtherCompensationAmt>0</OtherCompensationAmt>
      </Form990PartVIISectionAGrp>
      <Form990PartVIISectionAGrp>
        <PersonNm>Rebecca Griffin</PersonNm>
        <TitleTxt>Board Member</TitleTxt>
        <AverageHoursPerWeekRt>2.00</AverageHoursPerWeekRt>
        <AverageHoursPerWeekRltdOrgRt>0.00</AverageHoursPerWeekRltdOrgRt>
        <IndividualTrusteeOrDirectorInd>X</IndividualTrusteeOrDirectorInd>
        <ReportableCompFromOrgAmt>0</ReportableCompFromOrgAmt>
        <ReportableCompFromRltdOrgAmt>0</ReportableCompFromRltdOrgAmt>
        <OtherCompensationAmt>0</OtherCompensationAmt>
      </Form990PartVIISectionAGrp>
      <Form990PartVIISectionAGrp>
        <PersonNm>Sarah Hutchinson</PersonNm>
        <TitleTxt>Board Member</TitleTxt>
        <AverageHoursPerWeekRt>2.00</AverageHoursPerWeekRt>
        <AverageHoursPerWeekRltdOrgRt>0.00</AverageHoursPerWeekRltdOrgRt>
        <IndividualTrusteeOrDirectorInd>X</IndividualTrusteeOrDirectorInd>
        <ReportableCompFromOrgAmt>0</ReportableCompFromOrgAmt>
        <ReportableCompFromRltdOrgAmt>0</ReportableCompFromRltdOrgAmt>
        <OtherCompensationAmt>0</OtherCompensationAmt>
      </Form990PartVIISectionAGrp>
      <Form990PartVIISectionAGrp>
        <PersonNm>Larada Lee-Wallace</PersonNm>
        <TitleTxt>Board Member</TitleTxt>
        <AverageHoursPerWeekRt>2.00</AverageHoursPerWeekRt>
        <AverageHoursPerWeekRltdOrgRt>0.00</AverageHoursPerWeekRltdOrgRt>
        <IndividualTrusteeOrDirectorInd>X</IndividualTrusteeOrDirectorInd>
        <ReportableCompFromOrgAmt>0</ReportableCompFromOrgAmt>
        <ReportableCompFromRltdOrgAmt>0</ReportableCompFromRltdOrgAmt>
        <OtherCompensationAmt>0</OtherCompensationAmt>
      </Form990PartVIISectionAGrp>
      <TotalReportableCompFromOrgAmt>94665</TotalReportableCompFromOrgAmt>
      <IndivRcvdGreaterThan100KCnt>0</IndivRcvdGreaterThan100KCnt>
      <FormerOfcrEmployeesListedInd>false</FormerOfcrEmployeesListedInd>
      <TotalCompGreaterThan150KInd>false</TotalCompGreaterThan150KInd>
      <CompensationFromOtherSrcsInd>false</CompensationFromOtherSrcsInd>
      <CntrctRcvdGreaterThan100KCnt>0</CntrctRcvdGreaterThan100KCnt>
      <AllOtherContributionsAmt>1046560</AllOtherContributionsAmt>
      <TotalContributionsAmt>1046560</TotalContributionsAmt>
      <TotalProgramServiceRevenueAmt>0</TotalProgramServiceRevenueAmt>
      <InvestmentIncomeGrp>
        <TotalRevenueColumnAmt>685</TotalRevenueColumnAmt>
        <ExclusionAmt>685</ExclusionAmt>
      </InvestmentIncomeGrp>
      <IncmFromInvestBondProceedsGrp>
        <TotalRevenueColumnAmt>0</TotalRevenueColumnAmt>
      </IncmFromInvestBondProceedsGrp>
      <RoyaltiesRevenueGrp>
        <TotalRevenueColumnAmt>0</TotalRevenueColumnAmt>
      </RoyaltiesRevenueGrp>
      <NetRentalIncomeOrLossGrp>
        <TotalRevenueColumnAmt>0</TotalRevenueColumnAmt>
      </NetRentalIncomeOrLossGrp>
      <NetGainOrLossInvestmentsGrp>
        <TotalRevenueColumnAmt>0</TotalRevenueColumnAmt>
      </NetGainOrLossInvestmentsGrp>
      <FundraisingGrossIncomeAmt>61527</FundraisingGrossIncomeAmt>
      <FundraisingDirectExpensesAmt>882</FundraisingDirectExpensesAmt>
      <NetIncmFromFundraisingEvtGrp>
        <TotalRevenueColumnAmt>60645</TotalRevenueColumnAmt>
      </NetIncmFromFundraisingEvtGrp>
      <NetIncomeFromGamingGrp>
        <TotalRevenueColumnAmt>0</TotalRevenueColumnAmt>
      </NetIncomeFromGamingGrp>
      <NetIncomeOrLossGrp>
        <TotalRevenueColumnAmt>0</TotalRevenueColumnAmt>
      </NetIncomeOrLossGrp>
      <OtherRevenueMiscGrp>
        <Desc>Honorarium</Desc>
        <TotalRevenueColumnAmt>1000</TotalRevenueColumnAmt>
        <RelatedOrExemptFuncIncomeAmt>1000</RelatedOrExemptFuncIncomeAmt>
      </OtherRevenueMiscGrp>
      <OtherRevenueMiscGrp>
        <Desc>Miscellaneous</Desc>
        <TotalRevenueColumnAmt>2220</TotalRevenueColumnAmt>
        <RelatedOrExemptFuncIncomeAmt>2220</RelatedOrExemptFuncIncomeAmt>
      </OtherRevenueMiscGrp>
      <OtherRevenueTotalAmt>3220</OtherRevenueTotalAmt>
      <TotalRevenueGrp>
        <TotalRevenueColumnAmt>1111110</TotalRevenueColumnAmt>
        <RelatedOrExemptFuncIncomeAmt>3220</RelatedOrExemptFuncIncomeAmt>
        <ExclusionAmt>685</ExclusionAmt>
      </TotalRevenueGrp>
      <InfoInScheduleOPartIXInd>X</InfoInScheduleOPartIXInd>
      <GrantsToDomesticOrgsGrp>
        <TotalAmt>25000</TotalAmt>
        <ProgramServicesAmt>25000</ProgramServicesAmt>
      </GrantsToDomesticOrgsGrp>
      <GrantsToDomesticIndividualsGrp>
        <TotalAmt>2500</TotalAmt>
        <ProgramServicesAmt>2500</ProgramServicesAmt>
      </GrantsToDomesticIndividualsGrp>
      <ForeignGrantsGrp>
        <TotalAmt>0</TotalAmt>
      </ForeignGrantsGrp>
      <BenefitsToMembersGrp>
        <TotalAmt>0</TotalAmt>
      </BenefitsToMembersGrp>
      <CompCurrentOfcrDirectorsGrp>
        <TotalAmt>98325</TotalAmt>
        <ProgramServicesAmt>44246</ProgramServicesAmt>
        <ManagementAndGeneralAmt>29498</ManagementAndGeneralAmt>
        <FundraisingAmt>24581</FundraisingAmt>
      </CompCurrentOfcrDirectorsGrp>
      <CompDisqualPersonsGrp>
        <TotalAmt>0</TotalAmt>
      </CompDisqualPersonsGrp>
      <OtherSalariesAndWagesGrp>
        <TotalAmt>272693</TotalAmt>
        <ProgramServicesAmt>212961</ProgramServicesAmt>
        <ManagementAndGeneralAmt>44701</ManagementAndGeneralAmt>
        <FundraisingAmt>15031</FundraisingAmt>
      </OtherSalariesAndWagesGrp>
      <PensionPlanContributionsGrp>
        <TotalAmt>0</TotalAmt>
      </PensionPlanContributionsGrp>
      <OtherEmployeeBenefitsGrp>
        <TotalAmt>63279</TotalAmt>
        <ProgramServicesAmt>42972</ProgramServicesAmt>
        <ManagementAndGeneralAmt>15970</ManagementAndGeneralAmt>
        <FundraisingAmt>4337</FundraisingAmt>
      </OtherEmployeeBenefitsGrp>
      <PayrollTaxesGrp>
        <TotalAmt>32025</TotalAmt>
        <ProgramServicesAmt>22097</ProgramServicesAmt>
        <ManagementAndGeneralAmt>6405</ManagementAndGeneralAmt>
        <FundraisingAmt>3523</FundraisingAmt>
      </PayrollTaxesGrp>
      <FeesForServicesManagementGrp>
        <TotalAmt>0</TotalAmt>
      </FeesForServicesManagementGrp>
      <FeesForServicesLegalGrp>
        <TotalAmt>0</TotalAmt>
      </FeesForServicesLegalGrp>
      <FeesForServicesAccountingGrp>
        <TotalAmt>16339</TotalAmt>
        <ManagementAndGeneralAmt>16339</ManagementAndGeneralAmt>
      </FeesForServicesAccountingGrp>
      <FeesForServicesLobbyingGrp>
        <TotalAmt>0</TotalAmt>
      </FeesForServicesLobbyingGrp>
      <FeesForServicesProfFundraising>
        <TotalAmt>0</TotalAmt>
      </FeesForServicesProfFundraising>
      <FeesForSrvcInvstMgmntFeesGrp>
        <TotalAmt>0</TotalAmt>
      </FeesForSrvcInvstMgmntFeesGrp>
      <FeesForServicesOtherGrp>
        <TotalAmt>102485</TotalAmt>
        <ProgramServicesAmt>51896</ProgramServicesAmt>
        <ManagementAndGeneralAmt>38901</ManagementAndGeneralAmt>
        <FundraisingAmt>11688</FundraisingAmt>
      </FeesForServicesOtherGrp>
      <AdvertisingGrp>
        <TotalAmt>0</TotalAmt>
      </AdvertisingGrp>
      <OfficeExpensesGrp>
        <TotalAmt>10922</TotalAmt>
        <ProgramServicesAmt>254</ProgramServicesAmt>
        <ManagementAndGeneralAmt>10668</ManagementAndGeneralAmt>
      </OfficeExpensesGrp>
      <InformationTechnologyGrp>
        <TotalAmt>0</TotalAmt>
      </InformationTechnologyGrp>
      <RoyaltiesGrp>
        <TotalAmt>0</TotalAmt>
      </RoyaltiesGrp>
      <OccupancyGrp>
        <TotalAmt>28043</TotalAmt>
        <ProgramServicesAmt>19350</ProgramServicesAmt>
        <ManagementAndGeneralAmt>5608</ManagementAndGeneralAmt>
        <FundraisingAmt>3085</FundraisingAmt>
      </OccupancyGrp>
      <TravelGrp>
        <TotalAmt>3512</TotalAmt>
        <ProgramServicesAmt>453</ProgramServicesAmt>
        <ManagementAndGeneralAmt>3059</ManagementAndGeneralAmt>
      </TravelGrp>
      <PymtTravelEntrtnmntPubOfclGrp>
        <TotalAmt>0</TotalAmt>
      </PymtTravelEntrtnmntPubOfclGrp>
      <ConferencesMeetingsGrp>
        <TotalAmt>3884</TotalAmt>
        <ManagementAndGeneralAmt>3884</ManagementAndGeneralAmt>
      </ConferencesMeetingsGrp>
      <InterestGrp>
        <TotalAmt>0</TotalAmt>
      </InterestGrp>
      <PaymentsToAffiliatesGrp>
        <TotalAmt>0</TotalAmt>
      </PaymentsToAffiliatesGrp>
      <DepreciationDepletionGrp>
        <TotalAmt>0</TotalAmt>
      </DepreciationDepletionGrp>
      <InsuranceGrp>
        <TotalAmt>3483</TotalAmt>
        <ProgramServicesAmt>2403</ProgramServicesAmt>
        <ManagementAndGeneralAmt>697</ManagementAndGeneralAmt>
        <FundraisingAmt>383</FundraisingAmt>
      </InsuranceGrp>
      <OtherExpensesGrp>
        <Desc>Client Costs</Desc>
        <TotalAmt>108045</TotalAmt>
        <ProgramServicesAmt>108045</ProgramServicesAmt>
      </OtherExpensesGrp>
      <OtherExpensesGrp>
        <Desc>Web &amp; Online Service</Desc>
        <TotalAmt>13028</TotalAmt>
        <ProgramServicesAmt>2234</ProgramServicesAmt>
        <ManagementAndGeneralAmt>7206</ManagementAndGeneralAmt>
        <FundraisingAmt>3588</FundraisingAmt>
      </OtherExpensesGrp>
      <OtherExpensesGrp>
        <Desc>Marketing/Outreach</Desc>
        <TotalAmt>12439</TotalAmt>
        <ProgramServicesAmt>375</ProgramServicesAmt>
        <ManagementAndGeneralAmt>1737</ManagementAndGeneralAmt>
        <FundraisingAmt>10327</FundraisingAmt>
      </OtherExpensesGrp>
      <OtherExpensesGrp>
        <Desc>Payroll Processing Fees</Desc>
        <TotalAmt>4789</TotalAmt>
        <ManagementAndGeneralAmt>4789</ManagementAndGeneralAmt>
      </OtherExpensesGrp>
      <AllOtherExpensesGrp>
        <TotalAmt>11923</TotalAmt>
        <ProgramServicesAmt>445</ProgramServicesAmt>
        <ManagementAndGeneralAmt>11478</ManagementAndGeneralAmt>
      </AllOtherExpensesGrp>
      <TotalFunctionalExpensesGrp>
        <TotalAmt>812714</TotalAmt>
        <ProgramServicesAmt>535231</ProgramServicesAmt>
        <ManagementAndGeneralAmt>200940</ManagementAndGeneralAmt>
        <FundraisingAmt>76543</FundraisingAmt>
      </TotalFunctionalExpensesGrp>
      <CashNonInterestBearingGrp>
        <BOYAmt>964251</BOYAmt>
        <EOYAmt>1212215</EOYAmt>
      </CashNonInterestBearingGrp>
      <SavingsAndTempCashInvstGrp>
        <EOYAmt>0</EOYAmt>
      </SavingsAndTempCashInvstGrp>
      <PledgesAndGrantsReceivableGrp>
        <EOYAmt>0</EOYAmt>
      </PledgesAndGrantsReceivableGrp>
      <AccountsReceivableGrp>
        <BOYAmt>3341</BOYAmt>
        <EOYAmt>55568</EOYAmt>
      </AccountsReceivableGrp>
      <ReceivablesFromOfficersEtcGrp>
        <EOYAmt>0</EOYAmt>
      </ReceivablesFromOfficersEtcGrp>
      <RcvblFromDisqualifiedPrsnGrp>
        <EOYAmt>0</EOYAmt>
      </RcvblFromDisqualifiedPrsnGrp>
      <OthNotesLoansReceivableNetGrp>
        <EOYAmt>0</EOYAmt>
      </OthNotesLoansReceivableNetGrp>
      <InventoriesForSaleOrUseGrp>
        <EOYAmt>0</EOYAmt>
      </InventoriesForSaleOrUseGrp>
      <PrepaidExpensesDefrdChargesGrp>
        <BOYAmt>1630</BOYAmt>
        <EOYAmt>16433</EOYAmt>
      </PrepaidExpensesDefrdChargesGrp>
      <LandBldgEquipCostOrOtherBssAmt>26527</LandBldgEquipCostOrOtherBssAmt>
      <LandBldgEquipAccumDeprecAmt>26527</LandBldgEquipAccumDeprecAmt>
      <LandBldgEquipBasisNetGrp>
        <EOYAmt>0</EOYAmt>
      </LandBldgEquipBasisNetGrp>
      <InvestmentsPubTradedSecGrp>
        <EOYAmt>0</EOYAmt>
      </InvestmentsPubTradedSecGrp>
      <InvestmentsOtherSecuritiesGrp>
        <EOYAmt>0</EOYAmt>
      </InvestmentsOtherSecuritiesGrp>
      <InvestmentsProgramRelatedGrp>
        <EOYAmt>0</EOYAmt>
      </InvestmentsProgramRelatedGrp>
      <IntangibleAssetsGrp>
        <EOYAmt>0</EOYAmt>
      </IntangibleAssetsGrp>
      <OtherAssetsTotalGrp>
        <BOYAmt>1501</BOYAmt>
        <EOYAmt>3987</EOYAmt>
      </OtherAssetsTotalGrp>
      <TotalAssetsGrp>
        <BOYAmt>970723</BOYAmt>
        <EOYAmt>1288203</EOYAmt>
      </TotalAssetsGrp>
      <AccountsPayableAccrExpnssGrp>
        <BOYAmt>12524</BOYAmt>
        <EOYAmt>40135</EOYAmt>
      </AccountsPayableAccrExpnssGrp>
      <OtherLiabilitiesGrp>
        <BOYAmt>7058</BOYAmt>
        <EOYAmt>369</EOYAmt>
      </OtherLiabilitiesGrp>
      <TotalLiabilitiesGrp>
        <BOYAmt>19582</BOYAmt>
        <EOYAmt>40504</EOYAmt>
      </TotalLiabilitiesGrp>
      <OrganizationFollowsFASB117Ind>X</OrganizationFollowsFASB117Ind>
      <NoDonorRestrictionNetAssetsGrp>
        <BOYAmt>951141</BOYAmt>
        <EOYAmt>1247699</EOYAmt>
      </NoDonorRestrictionNetAssetsGrp>
      <TotalNetAssetsFundBalanceGrp>
        <BOYAmt>951141</BOYAmt>
        <EOYAmt>1247699</EOYAmt>
      </TotalNetAssetsFundBalanceGrp>
      <TotLiabNetAssetsFundBalanceGrp>
        <BOYAmt>970723</BOYAmt>
        <EOYAmt>1288203</EOYAmt>
      </TotLiabNetAssetsFundBalanceGrp>
      <ReconcilationRevenueExpnssAmt>298396</ReconcilationRevenueExpnssAmt>
      <PriorPeriodAdjustmentsAmt>-1838</PriorPeriodAdjustmentsAmt>
      <MethodOfAccountingAccrualInd>X</MethodOfAccountingAccrualInd>
      <AccountantCompileOrReviewInd>false</AccountantCompileOrReviewInd>
      <FSAuditedInd>false</FSAuditedInd>
      <FederalGrantAuditRequiredInd>false</FederalGrantAuditRequiredInd>
    </IRS990>
    <IRS990ScheduleA documentId="IRS990ScheduleA" softwareId="21013475" softwareVersionNum="2021v4.1">
      <PubliclySupportedOrg509a2Ind>X</PubliclySupportedOrg509a2Ind>
      <GiftsGrantsContrisRcvd509Grp>
        <CurrentTaxYearMinus4YearsAmt>562929</CurrentTaxYearMinus4YearsAmt>
        <CurrentTaxYearMinus3YearsAmt>395083</CurrentTaxYearMinus3YearsAmt>
        <CurrentTaxYearMinus2YearsAmt>504933</CurrentTaxYearMinus2YearsAmt>
        <CurrentTaxYearMinus1YearAmt>713042</CurrentTaxYearMinus1YearAmt>
        <CurrentTaxYearAmt>1046560</CurrentTaxYearAmt>
        <TotalAmt>3222547</TotalAmt>
      </GiftsGrantsContrisRcvd509Grp>
      <GrossReceiptsAdmissionsGrp>
        <TotalAmt>0</TotalAmt>
      </GrossReceiptsAdmissionsGrp>
      <GrossReceiptsNonUnrltBusGrp>
        <TotalAmt>0</TotalAmt>
      </GrossReceiptsNonUnrltBusGrp>
      <TaxRevLeviedOrgnztnlBnft509Grp>
        <TotalAmt>0</TotalAmt>
      </TaxRevLeviedOrgnztnlBnft509Grp>
      <GovtFurnSrvcFcltsVl509Grp>
        <TotalAmt>0</TotalAmt>
      </GovtFurnSrvcFcltsVl509Grp>
      <Total509Grp>
        <CurrentTaxYearMinus4YearsAmt>562929</CurrentTaxYearMinus4YearsAmt>
        <CurrentTaxYearMinus3YearsAmt>395083</CurrentTaxYearMinus3YearsAmt>
        <CurrentTaxYearMinus2YearsAmt>504933</CurrentTaxYearMinus2YearsAmt>
        <CurrentTaxYearMinus1YearAmt>713042</CurrentTaxYearMinus1YearAmt>
        <CurrentTaxYearAmt>1046560</CurrentTaxYearAmt>
        <TotalAmt>3222547</TotalAmt>
      </Total509Grp>
      <AmountsRcvdDsqlfyPersonGrp>
        <TotalAmt>0</TotalAmt>
      </AmountsRcvdDsqlfyPersonGrp>
      <SubstantialContributorsAmtGrp>
        <TotalAmt>0</TotalAmt>
      </SubstantialContributorsAmtGrp>
      <PublicSupportTotal509Amt>3222547</PublicSupportTotal509Amt>
      <GrossInvestmentIncome509Grp>
        <CurrentTaxYearMinus3YearsAmt>422</CurrentTaxYearMinus3YearsAmt>
        <CurrentTaxYearMinus2YearsAmt>1120</CurrentTaxYearMinus2YearsAmt>
        <CurrentTaxYearMinus1YearAmt>1017</CurrentTaxYearMinus1YearAmt>
        <CurrentTaxYearAmt>685</CurrentTaxYearAmt>
        <TotalAmt>3244</TotalAmt>
      </GrossInvestmentIncome509Grp>
      <Post1975UBTIGrp>
        <TotalAmt>0</TotalAmt>
      </Post1975UBTIGrp>
      <InvestmentIncomeAndUBTIGrp>
        <CurrentTaxYearMinus3YearsAmt>422</CurrentTaxYearMinus3YearsAmt>
        <CurrentTaxYearMinus2YearsAmt>1120</CurrentTaxYearMinus2YearsAmt>
        <CurrentTaxYearMinus1YearAmt>1017</CurrentTaxYearMinus1YearAmt>
        <CurrentTaxYearAmt>685</CurrentTaxYearAmt>
        <TotalAmt>3244</TotalAmt>
      </InvestmentIncomeAndUBTIGrp>
      <NetIncomeFromOtherUBIGrp>
        <TotalAmt>0</TotalAmt>
      </NetIncomeFromOtherUBIGrp>
      <OtherIncome509Grp>
        <CurrentTaxYearMinus4YearsAmt>-2891</CurrentTaxYearMinus4YearsAmt>
        <CurrentTaxYearMinus3YearsAmt>19699</CurrentTaxYearMinus3YearsAmt>
        <CurrentTaxYearMinus2YearsAmt>94936</CurrentTaxYearMinus2YearsAmt>
        <CurrentTaxYearMinus1YearAmt>24323</CurrentTaxYearMinus1YearAmt>
        <CurrentTaxYearAmt>64747</CurrentTaxYearAmt>
        <TotalAmt>200814</TotalAmt>
      </OtherIncome509Grp>
      <TotalSupportCalendarYearGrp>
        <CurrentTaxYearMinus4YearsAmt>560038</CurrentTaxYearMinus4YearsAmt>
        <CurrentTaxYearMinus3YearsAmt>415204</CurrentTaxYearMinus3YearsAmt>
        <CurrentTaxYearMinus2YearsAmt>600989</CurrentTaxYearMinus2YearsAmt>
        <CurrentTaxYearMinus1YearAmt>738382</CurrentTaxYearMinus1YearAmt>
        <CurrentTaxYearAmt>1111992</CurrentTaxYearAmt>
        <TotalAmt>3426605</TotalAmt>
      </TotalSupportCalendarYearGrp>
      <PublicSupportCY509Pct>0.94040</PublicSupportCY509Pct>
      <PublicSupportPY509Pct>0.99460</PublicSupportPY509Pct>
      <InvestmentIncomeCYPct>0.00090</InvestmentIncomeCYPct>
      <InvestmentIncomePYPct>0.00090</InvestmentIncomePYPct>
      <ThirtyThrPctSuprtTestsCY509Ind>X</ThirtyThrPctSuprtTestsCY509Ind>
    </IRS990ScheduleA>
    <IRS990ScheduleB documentId="IRS990ScheduleB" softwareId="21013475" softwareVersionNum="2021v4.1">
      <ContributorInformationGrp>
        <ContributorNum>RESTRICTED</ContributorNum>
        <ContributorBusinessName>
          <BusinessNameLine1>RESTRICTED</BusinessNameLine1>
        </ContributorBusinessName>
        <ContributorUSAddress>
          <AddressLine1>RESTRICTED</AddressLine1>
          <AddressLine2>RESTRICTED</AddressLine2>
          <City>RESTRICTED</City>
          <State>RESTRICTED</State>
          <ZIPCode>RESTRICTED</ZIPCode>
        </ContributorUSAddress>
        <TotalContributionsAmt>RESTRICTED</TotalContributionsAmt>
      </ContributorInformationGrp>
    </IRS990ScheduleB>
    <IRS990ScheduleD documentId="IRS990ScheduleD" softwareId="21013475" softwareVersionNum="2021v4.1">
      <OtherLandBuildingsGrp>
        <OtherCostOrOtherBasisAmt>26527</OtherCostOrOtherBasisAmt>
        <DepreciationAmt>26527</DepreciationAmt>
      </OtherLandBuildingsGrp>
      <OtherLiabilitiesOrgGrp>
        <Desc>Credit Card Payable</Desc>
        <Amt>369</Amt>
      </OtherLiabilitiesOrgGrp>
      <TotalLiabilityAmt>369</TotalLiabilityAmt>
    </IRS990ScheduleD>
    <IRS990ScheduleG documentId="IRS990ScheduleG" softwareId="21013475" softwareVersionNum="2021v4.1">
      <AgrmtProfFundraisingActyInd>false</AgrmtProfFundraisingActyInd>
      <FundraisingEventInformationGrp>
        <Event1Nm>Special Event</Event1Nm>
        <GrossReceiptsEvent1Amt>61527</GrossReceiptsEvent1Amt>
        <GrossRevenueEvent1Amt>61527</GrossRevenueEvent1Amt>
        <OtherDirectExpensesEvent1Amt>882</OtherDirectExpensesEvent1Amt>
        <GrossReceiptsTotalAmt>61527</GrossReceiptsTotalAmt>
        <GrossRevenueTotalEventsAmt>61527</GrossRevenueTotalEventsAmt>
        <OthDirectExpnssTotalEventsAmt>882</OthDirectExpnssTotalEventsAmt>
        <DirectExpenseSummaryEventsAmt>882</DirectExpenseSummaryEventsAmt>
        <NetIncomeSummaryAmt>60645</NetIncomeSummaryAmt>
      </FundraisingEventInformationGrp>
    </IRS990ScheduleG>
    <IRS990ScheduleO documentId="IRS990ScheduleO" softwareId="21013475" softwareVersionNum="2021v4.1">
      <SupplementalInformationDetail>
        <FormAndLineReferenceDesc>Form 990, Part VI, Line 11b: Form 990 Review Process</FormAndLineReferenceDesc>
        <ExplanationTxt>The 990 is reviewed by the Board of Directors</ExplanationTxt>
      </SupplementalInformationDetail>
      <SupplementalInformationDetail>
        <FormAndLineReferenceDesc>Form 990, Part VI, Line 12c: Explanation of Monitoring and Enforcement of Conflicts</FormAndLineReferenceDesc>
        <ExplanationTxt>The organization requires notification of any conflicts of interest and requires members to abstain from participating in conversations and voting on any decisions that may present a conflict.</ExplanationTxt>
      </SupplementalInformationDetail>
      <SupplementalInformationDetail>
        <FormAndLineReferenceDesc>Form 990, Part VI, Line 15a: Compensation Review &amp; Approval Process - CEO, Top Management</FormAndLineReferenceDesc>
        <ExplanationTxt>State Comparison and Peer Review</ExplanationTxt>
      </SupplementalInformationDetail>
      <SupplementalInformationDetail>
        <FormAndLineReferenceDesc>Form 990, Part VI, Line 19: Other Organization Documents Publicly Available</FormAndLineReferenceDesc>
        <ExplanationTxt>Documents are provided, if requested.</ExplanationTxt>
      </SupplementalInformationDetail>
    </IRS990ScheduleO>
  </ReturnData>
</Return>
