<?xml version="1.0" encoding="utf-8"?>
<Return xmlns="http://www.irs.gov/efile" xmlns:xsi="http://www.w3.org/2001/XMLSchema-instance" xsi:schemaLocation="http://www.irs.gov/efile" returnVersion="2022v5.0">
  <ReturnHeader binaryAttachmentCnt="0">
    <ReturnTs>2023-05-31T16:42:00-05:00</ReturnTs>
    <TaxPeriodEndDt>2022-12-31</TaxPeriodEndDt>
    <PreparerFirmGrp>
      <PreparerFirmEIN>390974031</PreparerFirmEIN>
      <PreparerFirmName>
        <BusinessNameLine1Txt>WEGNER CPAS LLP</BusinessNameLine1Txt>
      </PreparerFirmName>
      <PreparerUSAddress>
        <AddressLine1Txt>2921 LANDMARK PL STE 300</AddressLine1Txt>
        <CityNm>MADISON</CityNm>
        <StateAbbreviationCd>WI</StateAbbreviationCd>
        <ZIPCd>537134236</ZIPCd>
      </PreparerUSAddress>
    </PreparerFirmGrp>
    <ReturnTypeCd>990EZ</ReturnTypeCd>
    <TaxPeriodBeginDt>2022-01-01</TaxPeriodBeginDt>
    <Filer>
      <EIN>815284790</EIN>
      <BusinessName>
        <BusinessNameLine1Txt>WISCONSIN FAITH VOICES FOR JUSTICE</BusinessNameLine1Txt>
      </BusinessName>
      <BusinessNameControlTxt>WISC</BusinessNameControlTxt>
      <PhoneNum>6085137121</PhoneNum>
      <USAddress>
        <AddressLine1Txt>7118 OLD SAUK RD</AddressLine1Txt>
        <CityNm>MADISON</CityNm>
        <StateAbbreviationCd>WI</StateAbbreviationCd>
        <ZIPCd>53717</ZIPCd>
      </USAddress>
    </Filer>
    <BusinessOfficerGrp>
      <PersonNm>RABBI BONNIE MARGULIS</PersonNm>
      <PersonTitleTxt>EXECUTIVE DIRECTOR</PersonTitleTxt>
      <PhoneNum>6085137121</PhoneNum>
      <SignatureDt>2023-05-31</SignatureDt>
      <DiscussWithPaidPreparerInd>1</DiscussWithPaidPreparerInd>
    </BusinessOfficerGrp>
    <SigningOfficerGrp>
      <PersonFullName>
        <PersonFirstNm>RABBI</PersonFirstNm>
        <PersonLastNm>BONNIE MARGULIS</PersonLastNm>
      </PersonFullName>
      <SSN>999009999</SSN>
    </SigningOfficerGrp>
    <IRSResponsiblePrtyInfoCurrInd>0</IRSResponsiblePrtyInfoCurrInd>
    <PreparerPersonGrp>
      <PreparerPersonNm>AMANDA VANNATTA CPA</PreparerPersonNm>
      <PTIN>P00948755</PTIN>
      <PhoneNum>6082744020</PhoneNum>
      <PreparationDt>2023-05-31</PreparationDt>
    </PreparerPersonGrp>
    <AdditionalFilerInformation>
      <TrustedCustomerGrp>
        <TrustedCustomerCd>2</TrustedCustomerCd>
        <AuthenticationAssuranceLevelCd>AAL1</AuthenticationAssuranceLevelCd>
        <IdentityAssuranceLevelCd>IAL1</IdentityAssuranceLevelCd>
      </TrustedCustomerGrp>
    </AdditionalFilerInformation>
    <TaxYr>2022</TaxYr>
    <BuildTS>2023-04-26 12:10:37Z</BuildTS>
  </ReturnHeader>
  <ReturnData documentCnt="6">
    <IRS990EZ documentId="RetDoc1234200001" referenceDocumentId="RetDoc1051800001 RetDoc2278000001">
      <AddressChangeInd>X</AddressChangeInd>
      <MethodOfAccountingCashInd>X</MethodOfAccountingCashInd>
      <WebsiteAddressTxt>WWW.WISCONSINFAITHVOICESFORJUSTICE.ORG/</WebsiteAddressTxt>
      <Organization501c3Ind referenceDocumentId="RetDoc1039100001">X</Organization501c3Ind>
      <TypeOfOrganizationOtherInd>X</TypeOfOrganizationOtherInd>
      <TypeOfOrganizationOtherDesc>UNINCORPORATED ASSOCIATIONS</TypeOfOrganizationOtherDesc>
      <GrossReceiptsAmt>162400</GrossReceiptsAmt>
      <InfoInScheduleOPartIInd>X</InfoInScheduleOPartIInd>
      <ContributionsGiftsGrantsEtcAmt>162363</ContributionsGiftsGrantsEtcAmt>
      <InvestmentIncomeAmt>37</InvestmentIncomeAmt>
      <TotalRevenueAmt>162400</TotalRevenueAmt>
      <GrantsAndSimilarAmountsPaidAmt>17160</GrantsAndSimilarAmountsPaidAmt>
      <SalariesOtherCompEmplBnftAmt>45060</SalariesOtherCompEmplBnftAmt>
      <FeesAndOtherPymtToIndCntrctAmt>43024</FeesAndOtherPymtToIndCntrctAmt>
      <PrintingPublicationsPostageAmt>10637</PrintingPublicationsPostageAmt>
      <OtherExpensesTotalAmt>10726</OtherExpensesTotalAmt>
      <TotalExpensesAmt>126607</TotalExpensesAmt>
      <ExcessOrDeficitForYearAmt>35793</ExcessOrDeficitForYearAmt>
      <NetAssetsOrFundBalancesBOYAmt>110012</NetAssetsOrFundBalancesBOYAmt>
      <OtherChangesInNetAssetsAmt>0</OtherChangesInNetAssetsAmt>
      <NetAssetsOrFundBalancesEOYAmt>145805</NetAssetsOrFundBalancesEOYAmt>
      <InfoInScheduleOPartIIInd>X</InfoInScheduleOPartIIInd>
      <CashSavingsAndInvestmentsGrp>
        <BOYAmt>111115</BOYAmt>
        <EOYAmt>145805</EOYAmt>
      </CashSavingsAndInvestmentsGrp>
      <Form990TotalAssetsGrp>
        <BOYAmt>111115</BOYAmt>
        <EOYAmt>145805</EOYAmt>
      </Form990TotalAssetsGrp>
      <SumOfTotalLiabilitiesGrp>
        <BOYAmt>1103</BOYAmt>
        <EOYAmt>0</EOYAmt>
      </SumOfTotalLiabilitiesGrp>
      <NetAssetsOrFundBalancesGrp>
        <BOYAmt>110012</BOYAmt>
        <EOYAmt>145805</EOYAmt>
      </NetAssetsOrFundBalancesGrp>
      <InfoInScheduleOPartIIIInd>X</InfoInScheduleOPartIIIInd>
      <PrimaryExemptPurposeTxt>THE MISSION OF WISCONSIN FAITH VOICES FOR JUSTICE IS TO CONNECT AND EMPOWER FAITH COMMUNITIES AND INDIVIDUALS TO WORK FOR THE COMMON GOOD AND A LIFE OF DIGNITY FOR EVERYONE. WE ADVOCATE FOR CHANGE SO THAT ALL INDIVIDUALS AND FAMILIES CAN THRIVE SOCIALLY, PROSPER ECONOMICALLY, AND PARTICIPATE FULLY IN CIVIL SOCIETY. WE INTENTIONALLY BUILD BRIDGES ACROSS FAITH COMMUNITIES AND DRAW ON THE COLLECTIVE WISDOM, COURAGE, AND STRENGTH OF OUR VARIOUS FAITH TRADITIONS.</PrimaryExemptPurposeTxt>
      <ProgramSrvcAccomplishmentGrp>
        <DescriptionProgramSrvcAccomTxt>INTERFAITH COMMUNITY BUILDING - WE ORGANIZE CLERGY AND CONGREGATIONS TO WORK TOGETHER FOR THE COMMON GOOD. AS PART OF THIS EFFORT, WE SPONSOR INTERFAITH ACTIVITIES TO BUILD BRIDGES AMONG FAITHS, TO BRING TOGETHER INDIVIDUALS OF DIFFERENT FAITHS TO LEARN ABOUT EACH OTHER'S FAITH TRADITIONS AND TO BUILD RELATIONSHIPS ACROSS FAITHS.</DescriptionProgramSrvcAccomTxt>
        <GrantsAndAllocationsAmt>17160</GrantsAndAllocationsAmt>
        <ProgramServiceExpensesAmt>37372</ProgramServiceExpensesAmt>
      </ProgramSrvcAccomplishmentGrp>
      <ProgramSrvcAccomplishmentGrp>
        <DescriptionProgramSrvcAccomTxt>WISCONSIN INTERFAITH VOTER ENGAGEMENT CAMPAIGN IN PARTNERSHIP WITH THE WISCONSIN COUNCIL OF CHURCHES IS A NON-PARTISAN PROJECT TO ORGANIZE CLERGY AND CONGREGATIONS TO WORK ON VOTER EDUCATION, VOTER REGISTRATION, AND GET OUT THE VOTE EFFORTS.</DescriptionProgramSrvcAccomTxt>
        <GrantsAndAllocationsAmt>0</GrantsAndAllocationsAmt>
        <ProgramServiceExpensesAmt>17202</ProgramServiceExpensesAmt>
      </ProgramSrvcAccomplishmentGrp>
      <ProgramSrvcAccomplishmentGrp>
        <DescriptionProgramSrvcAccomTxt>DANE SANCTUARY COALITION - PROVIDES SANCTUARY FOR THOSE FACING DEPORTATION; ADVOCATES FOR JUSTICE FOR UNDOCUMENTED IMMIGRANTS, ASYLUM SEEKERS, AND REFUGEES; ASSISTS WITH TEMPORARY HOUSING; PROVIDES RIDES TO ICE CHECK-INS AND IMMIGRATION HEARINGS; AND EDUCATES THE PUBLIC ON IMMIGRATION ISSUES.</DescriptionProgramSrvcAccomTxt>
        <GrantsAndAllocationsAmt>0</GrantsAndAllocationsAmt>
        <ProgramServiceExpensesAmt>9012</ProgramServiceExpensesAmt>
      </ProgramSrvcAccomplishmentGrp>
      <ProgramSrvcAccomplishmentGrp>
        <DescriptionProgramSrvcAccomTxt>OTHER PROGRAMS.</DescriptionProgramSrvcAccomTxt>
        <GrantsAndAllocationsAmt>0</GrantsAndAllocationsAmt>
        <ProgramServiceExpensesAmt>6448</ProgramServiceExpensesAmt>
      </ProgramSrvcAccomplishmentGrp>
      <TotalProgramServiceExpensesAmt>70034</TotalProgramServiceExpensesAmt>
      <OfficerDirectorTrusteeEmplGrp>
        <PersonNm>RABBI BONNIE MARGULIS</PersonNm>
        <TitleTxt>EXECUTIVE DIRECTOR</TitleTxt>
        <AverageHrsPerWkDevotedToPosRt>50.00</AverageHrsPerWkDevotedToPosRt>
        <CompensationAmt>40000</CompensationAmt>
        <EmployeeBenefitProgramAmt>2000</EmployeeBenefitProgramAmt>
        <ExpenseAccountOtherAllwncAmt>0</ExpenseAccountOtherAllwncAmt>
      </OfficerDirectorTrusteeEmplGrp>
      <OfficerDirectorTrusteeEmplGrp>
        <PersonNm>REVEREND LARRY SEXE</PersonNm>
        <TitleTxt>PRESIDENT</TitleTxt>
        <AverageHrsPerWkDevotedToPosRt>1.00</AverageHrsPerWkDevotedToPosRt>
        <CompensationAmt>0</CompensationAmt>
        <EmployeeBenefitProgramAmt>0</EmployeeBenefitProgramAmt>
        <ExpenseAccountOtherAllwncAmt>0</ExpenseAccountOtherAllwncAmt>
      </OfficerDirectorTrusteeEmplGrp>
      <OfficerDirectorTrusteeEmplGrp>
        <PersonNm>VICKI BERENSON</PersonNm>
        <TitleTxt>SECRETARY</TitleTxt>
        <AverageHrsPerWkDevotedToPosRt>2.00</AverageHrsPerWkDevotedToPosRt>
        <CompensationAmt>0</CompensationAmt>
        <EmployeeBenefitProgramAmt>0</EmployeeBenefitProgramAmt>
        <ExpenseAccountOtherAllwncAmt>0</ExpenseAccountOtherAllwncAmt>
      </OfficerDirectorTrusteeEmplGrp>
      <OfficerDirectorTrusteeEmplGrp>
        <PersonNm>DAVID CHAIMSON</PersonNm>
        <TitleTxt>MEMBER</TitleTxt>
        <AverageHrsPerWkDevotedToPosRt>1.00</AverageHrsPerWkDevotedToPosRt>
        <CompensationAmt>0</CompensationAmt>
        <EmployeeBenefitProgramAmt>0</EmployeeBenefitProgramAmt>
        <ExpenseAccountOtherAllwncAmt>0</ExpenseAccountOtherAllwncAmt>
      </OfficerDirectorTrusteeEmplGrp>
      <OfficerDirectorTrusteeEmplGrp>
        <PersonNm>REVEREND SELENA FOX</PersonNm>
        <TitleTxt>MEMBER</TitleTxt>
        <AverageHrsPerWkDevotedToPosRt>1.00</AverageHrsPerWkDevotedToPosRt>
        <CompensationAmt>0</CompensationAmt>
        <EmployeeBenefitProgramAmt>0</EmployeeBenefitProgramAmt>
        <ExpenseAccountOtherAllwncAmt>0</ExpenseAccountOtherAllwncAmt>
      </OfficerDirectorTrusteeEmplGrp>
      <OfficerDirectorTrusteeEmplGrp>
        <PersonNm>REVEREND NICK UTPHALL</PersonNm>
        <TitleTxt>MEMBER</TitleTxt>
        <AverageHrsPerWkDevotedToPosRt>1.00</AverageHrsPerWkDevotedToPosRt>
        <CompensationAmt>0</CompensationAmt>
        <EmployeeBenefitProgramAmt>0</EmployeeBenefitProgramAmt>
        <ExpenseAccountOtherAllwncAmt>0</ExpenseAccountOtherAllwncAmt>
      </OfficerDirectorTrusteeEmplGrp>
      <OfficerDirectorTrusteeEmplGrp>
        <PersonNm>REVEREND WILLIE BRISCO</PersonNm>
        <TitleTxt>MEMBER</TitleTxt>
        <AverageHrsPerWkDevotedToPosRt>1.00</AverageHrsPerWkDevotedToPosRt>
        <CompensationAmt>0</CompensationAmt>
        <EmployeeBenefitProgramAmt>0</EmployeeBenefitProgramAmt>
        <ExpenseAccountOtherAllwncAmt>0</ExpenseAccountOtherAllwncAmt>
      </OfficerDirectorTrusteeEmplGrp>
      <OfficerDirectorTrusteeEmplGrp>
        <PersonNm>REVEREND KARLA GARCIA</PersonNm>
        <TitleTxt>MEMBER</TitleTxt>
        <AverageHrsPerWkDevotedToPosRt>1.00</AverageHrsPerWkDevotedToPosRt>
        <CompensationAmt>0</CompensationAmt>
        <EmployeeBenefitProgramAmt>0</EmployeeBenefitProgramAmt>
        <ExpenseAccountOtherAllwncAmt>0</ExpenseAccountOtherAllwncAmt>
      </OfficerDirectorTrusteeEmplGrp>
      <OfficerDirectorTrusteeEmplGrp>
        <PersonNm>RABBI MARC BERKSON</PersonNm>
        <TitleTxt>MEMBER</TitleTxt>
        <AverageHrsPerWkDevotedToPosRt>1.00</AverageHrsPerWkDevotedToPosRt>
        <CompensationAmt>0</CompensationAmt>
        <EmployeeBenefitProgramAmt>0</EmployeeBenefitProgramAmt>
        <ExpenseAccountOtherAllwncAmt>0</ExpenseAccountOtherAllwncAmt>
      </OfficerDirectorTrusteeEmplGrp>
      <OfficerDirectorTrusteeEmplGrp>
        <PersonNm>CHARLES COHEN</PersonNm>
        <TitleTxt>MEMBER</TitleTxt>
        <AverageHrsPerWkDevotedToPosRt>2.00</AverageHrsPerWkDevotedToPosRt>
        <CompensationAmt>0</CompensationAmt>
        <EmployeeBenefitProgramAmt>0</EmployeeBenefitProgramAmt>
        <ExpenseAccountOtherAllwncAmt>0</ExpenseAccountOtherAllwncAmt>
      </OfficerDirectorTrusteeEmplGrp>
      <OfficerDirectorTrusteeEmplGrp>
        <PersonNm>ADAM CLAUSEN</PersonNm>
        <TitleTxt>MEMBER</TitleTxt>
        <AverageHrsPerWkDevotedToPosRt>1.00</AverageHrsPerWkDevotedToPosRt>
        <CompensationAmt>0</CompensationAmt>
        <EmployeeBenefitProgramAmt>0</EmployeeBenefitProgramAmt>
        <ExpenseAccountOtherAllwncAmt>0</ExpenseAccountOtherAllwncAmt>
      </OfficerDirectorTrusteeEmplGrp>
      <InfoInScheduleOPartVInd>X</InfoInScheduleOPartVInd>
      <ActivitiesNotPreviouslyRptInd>0</ActivitiesNotPreviouslyRptInd>
      <ChgMadeToOrgnzngDocNotRptInd>1</ChgMadeToOrgnzngDocNotRptInd>
      <OrganizationHadUBIInd>0</OrganizationHadUBIInd>
      <SubjectToProxyTaxInd referenceDocumentId="RetDoc1039700001">0</SubjectToProxyTaxInd>
      <OrganizationDissolvedEtcInd>0</OrganizationDissolvedEtcInd>
      <DirectIndirectPltclExpendAmt>0</DirectIndirectPltclExpendAmt>
      <MadeLoansToFromOfficersInd>0</MadeLoansToFromOfficersInd>
      <TaxImposedUnderIRC4911Amt>0</TaxImposedUnderIRC4911Amt>
      <TaxImposedUnderIRC4912Amt>0</TaxImposedUnderIRC4912Amt>
      <TaxImposedUnderIRC4955Amt>0</TaxImposedUnderIRC4955Amt>
      <EngagedInExcessBenefitTransInd>0</EngagedInExcessBenefitTransInd>
      <TaxImposedOnOrganizationMgrAmt>0</TaxImposedOnOrganizationMgrAmt>
      <TaxReimbursedByOrganizationAmt>0</TaxReimbursedByOrganizationAmt>
      <ProhibitedTaxShelterTransInd>0</ProhibitedTaxShelterTransInd>
      <StatesWhereCopyOfReturnIsFldCd>WI</StatesWhereCopyOfReturnIsFldCd>
      <BooksInCareOfDetail>
        <PersonNm>RABBI BONNIE MARGULIS</PersonNm>
        <USAddress>
          <AddressLine1Txt>7118 OLD SAUK RD</AddressLine1Txt>
          <CityNm>MADISON</CityNm>
          <StateAbbreviationCd>WI</StateAbbreviationCd>
          <ZIPCd>53717</ZIPCd>
        </USAddress>
        <PhoneNum>6085137121</PhoneNum>
      </BooksInCareOfDetail>
      <ForeignFinancialAccountInd>0</ForeignFinancialAccountInd>
      <ForeignOfficeInd>0</ForeignOfficeInd>
      <DonorAdvisedFndsInd>0</DonorAdvisedFndsInd>
      <OperateHospitalInd>0</OperateHospitalInd>
      <TanningServicesProvidedInd>0</TanningServicesProvidedInd>
      <RelatedOrganizationCtrlEntInd>0</RelatedOrganizationCtrlEntInd>
      <TransactionWithControlEntInd>0</TransactionWithControlEntInd>
      <PoliticalCampaignActyInd referenceDocumentId="RetDoc1039700001">0</PoliticalCampaignActyInd>
      <LobbyingActivitiesInd referenceDocumentId="RetDoc1039700001">1</LobbyingActivitiesInd>
      <SchoolOperatingInd>0</SchoolOperatingInd>
      <TrnsfrExmptNonChrtblRltdOrgInd>0</TrnsfrExmptNonChrtblRltdOrgInd>
      <PartVIOfCompOfHghstPdEmplTxt>NONE</PartVIOfCompOfHghstPdEmplTxt>
      <OtherEmployeePaidOver100kCnt>0</OtherEmployeePaidOver100kCnt>
      <PartVIHghstPdCntrctProfSrvcTxt>NONE</PartVIHghstPdCntrctProfSrvcTxt>
      <CntrctRcvdGreaterThan100KCnt>0</CntrctRcvdGreaterThan100KCnt>
      <FiledScheduleAInd>1</FiledScheduleAInd>
    </IRS990EZ>
    <IRS990ScheduleA documentId="RetDoc1039100001">
      <PublicOrganization170Ind>X</PublicOrganization170Ind>
      <GiftsGrantsContriRcvd170Grp>
        <CurrentTaxYearMinus4YearsAmt>10885</CurrentTaxYearMinus4YearsAmt>
        <CurrentTaxYearMinus3YearsAmt>106773</CurrentTaxYearMinus3YearsAmt>
        <CurrentTaxYearMinus2YearsAmt>110286</CurrentTaxYearMinus2YearsAmt>
        <CurrentTaxYearMinus1YearAmt>115993</CurrentTaxYearMinus1YearAmt>
        <CurrentTaxYearAmt>162363</CurrentTaxYearAmt>
        <TotalAmt>506300</TotalAmt>
      </GiftsGrantsContriRcvd170Grp>
      <TotalCalendarYear170Grp>
        <CurrentTaxYearMinus4YearsAmt>10885</CurrentTaxYearMinus4YearsAmt>
        <CurrentTaxYearMinus3YearsAmt>106773</CurrentTaxYearMinus3YearsAmt>
        <CurrentTaxYearMinus2YearsAmt>110286</CurrentTaxYearMinus2YearsAmt>
        <CurrentTaxYearMinus1YearAmt>115993</CurrentTaxYearMinus1YearAmt>
        <CurrentTaxYearAmt>162363</CurrentTaxYearAmt>
        <TotalAmt>506300</TotalAmt>
      </TotalCalendarYear170Grp>
      <SubstantialContributorsTotAmt>232740</SubstantialContributorsTotAmt>
      <PublicSupportTotal170Amt>273560</PublicSupportTotal170Amt>
      <GrossInvestmentIncome170Grp>
        <CurrentTaxYearMinus4YearsAmt>15</CurrentTaxYearMinus4YearsAmt>
        <CurrentTaxYearMinus3YearsAmt>55</CurrentTaxYearMinus3YearsAmt>
        <CurrentTaxYearMinus2YearsAmt>67</CurrentTaxYearMinus2YearsAmt>
        <CurrentTaxYearMinus1YearAmt>31</CurrentTaxYearMinus1YearAmt>
        <CurrentTaxYearAmt>37</CurrentTaxYearAmt>
        <TotalAmt>205</TotalAmt>
      </GrossInvestmentIncome170Grp>
      <TotalSupportAmt>506505</TotalSupportAmt>
      <PublicSupportCY170Pct>0.54010</PublicSupportCY170Pct>
      <ThirtyThrPctSuprtTestsCY170Ind>X</ThirtyThrPctSuprtTestsCY170Ind>
      <PublicSupportPY509Pct>0.99950</PublicSupportPY509Pct>
      <InvestmentIncomePYPct>0.00050</InvestmentIncomePYPct>
    </IRS990ScheduleA>
    <IRS990ScheduleB documentId="RetDoc1234500001">
      <ContributorInformationGrp>
        <ContributorNum>RESTRICTED</ContributorNum>
        <ContributorBusinessName>
          <BusinessNameLine1>RESTRICTED</BusinessNameLine1>
        </ContributorBusinessName>
        <ContributorUSAddress>
          <AddressLine1>RESTRICTED</AddressLine1>
          <AddressLine2>RESTRICTED</AddressLine2>
          <City>RESTRICTED</City>
          <State>RESTRICTED</State>
          <ZIPCode>RESTRICTED</ZIPCode>
        </ContributorUSAddress>
        <TotalContributionsAmt>RESTRICTED</TotalContributionsAmt>
      </ContributorInformationGrp>
    </IRS990ScheduleB>
    <IRS990ScheduleC documentId="RetDoc1039700001">
      <VolunteersInd>0</VolunteersInd>
      <PaidStaffOrManagementInd>1</PaidStaffOrManagementInd>
      <MediaAdvertisementsInd>0</MediaAdvertisementsInd>
      <MailingsMembersInd>0</MailingsMembersInd>
      <PublicationsOrBroadcastInd>0</PublicationsOrBroadcastInd>
      <GrantsOtherOrganizationsInd>0</GrantsOtherOrganizationsInd>
      <DirectContactLegislatorsInd>1</DirectContactLegislatorsInd>
      <DirectContactLegislatorsAmt>22</DirectContactLegislatorsAmt>
      <RalliesDemonstrationsInd>1</RalliesDemonstrationsInd>
      <RalliesDemonstrationsAmt>22</RalliesDemonstrationsAmt>
      <OtherActivitiesInd>1</OtherActivitiesInd>
      <OtherActivitiesAmt>209</OtherActivitiesAmt>
      <TotalLobbyingExpendituresAmt>253</TotalLobbyingExpendituresAmt>
      <NotDescribedSection501c3Ind>0</NotDescribedSection501c3Ind>
      <SupplementalInformationDetail>
        <FormAndLineReferenceDesc>PART II-B, LINE 1:</FormAndLineReferenceDesc>
        <ExplanationTxt>HEALTHY SCHOOL MEALS ACT COALITION WEBINAR AND POSTS IN E-NEWS, AFGHAN ADJUSTMENT ACT ACTION ALERT, E-NEWS POST OPPOSING FOODSHARE REQUIREMENTS, LOBBY DAY WITH VOICES.</ExplanationTxt>
      </SupplementalInformationDetail>
    </IRS990ScheduleC>
    <IRS990ScheduleO documentId="RetDoc1051800001">
      <SupplementalInformationDetail>
        <FormAndLineReferenceDesc>FORM 990-EZ, PART I, LINE 4 - OTHER INVESTMENT INCOME</FormAndLineReferenceDesc>
        <ExplanationTxt>DESCRIPTION: INTEREST INCOME. AMOUNT: 37.</ExplanationTxt>
      </SupplementalInformationDetail>
      <SupplementalInformationDetail>
        <FormAndLineReferenceDesc>FORM 990-EZ, PART I, LINE 10 - GRANTS AND SIMILAR AMOUNTS PAID</FormAndLineReferenceDesc>
        <ExplanationTxt>ACTIVITY CLASSIFICATION: . GRANTEE NAME: WISCONSIN COUNCIL OF CHURCHES. GRANTEE ADDRESS: 30 W MIFFLIN ST #602 MADISON, WI 53703. AMOUNT GIVEN: 17,160.</ExplanationTxt>
      </SupplementalInformationDetail>
      <SupplementalInformationDetail>
        <FormAndLineReferenceDesc>FORM 990-EZ, PART I, LINE 16 - OTHER EXPENSES</FormAndLineReferenceDesc>
        <ExplanationTxt>DESCRIPTION: OFFICE EXPENSES. AMOUNT: 6,426. DESCRIPTION: INSURANCE. AMOUNT: 1,744. DESCRIPTION: INFORMATION TECHNOLOGY. AMOUNT: 29. DESCRIPTION: REIMBURSEMENTS. AMOUNT: 2,527. TOTAL TO FORM 990-EZ, LINE 16: 10,726.</ExplanationTxt>
      </SupplementalInformationDetail>
      <SupplementalInformationDetail>
        <FormAndLineReferenceDesc>FORM 990-EZ, PART II, LINE 26 - OTHER LIABILITIES</FormAndLineReferenceDesc>
        <ExplanationTxt>DESCRIPTION: ACCOUNTS PAYABLE AND ACCRUED EXPENSES. BEG. OF YEAR AMOUNT: 1,103. END OF YEAR AMOUNT: 0.</ExplanationTxt>
      </SupplementalInformationDetail>
      <SupplementalInformationDetail>
        <FormAndLineReferenceDesc>FORM 990-EZ, PAGE 3, PART V, LINE 34</FormAndLineReferenceDesc>
        <ExplanationTxt>THE ORGANIZATION AMENDED ITS BYLAWS TO UPDATE ITS MISSION STATEMENT AND TO UPDATE THE ROLES OF THE BOARD MEMBERS.</ExplanationTxt>
      </SupplementalInformationDetail>
    </IRS990ScheduleO>
    <TransferPrsnlBnftContractsDecl documentId="RetDoc2278000001">
      <DeclarationDesc>THE ORGANIZATION DID NOT, DURING THE YEAR, RECEIVE ANY FUNDS, DIRECTLY,OR INDIRECTLY, TO PAY PREMIUMS ON A PERSONAL BENEFIT CONTRACT.THE ORGANIZATION, DID NOT, DURING THE YEAR, PAY ANY PREMIUMS, DIRECTLY,OR INDIRECTLY, ON A PERSONAL BENEFIT CONTRACT.</DeclarationDesc>
    </TransferPrsnlBnftContractsDecl>
  </ReturnData>
</Return>
