<?xml version="1.0" encoding="utf-8"?>
<Return xmlns="http://www.irs.gov/efile" xmlns:xsi="http://www.w3.org/2001/XMLSchema-instance" xsi:schemaLocation="http://www.irs.gov/efile" returnVersion="2021v4.2">
  <ReturnHeader binaryAttachmentCnt="0">
    <ReturnTs>2023-02-14T16:41:27-06:00</ReturnTs>
    <TaxPeriodEndDt>2022-09-30</TaxPeriodEndDt>
    <PreparerFirmGrp>
      <PreparerFirmEIN>910189318</PreparerFirmEIN>
      <PreparerFirmName>
        <BusinessNameLine1Txt>MOSS ADAMS LLP</BusinessNameLine1Txt>
      </PreparerFirmName>
      <PreparerUSAddress>
        <AddressLine1Txt>2707 COLBY AVENUE SUITE 801</AddressLine1Txt>
        <CityNm>EVERETT</CityNm>
        <StateAbbreviationCd>WA</StateAbbreviationCd>
        <ZIPCd>98201</ZIPCd>
      </PreparerUSAddress>
    </PreparerFirmGrp>
    <ReturnTypeCd>990</ReturnTypeCd>
    <TaxPeriodBeginDt>2021-10-01</TaxPeriodBeginDt>
    <Filer>
      <EIN>911252785</EIN>
      <BusinessName>
        <BusinessNameLine1Txt>NORTHWEST REGIONAL PRIMARY CARE ASSOCIAT</BusinessNameLine1Txt>
      </BusinessName>
      <BusinessNameControlTxt>NORT</BusinessNameControlTxt>
      <PhoneNum>2067833004</PhoneNum>
      <USAddress>
        <AddressLine1Txt>200 WEST THOMAS STREET STE 330</AddressLine1Txt>
        <CityNm>SEATTLE</CityNm>
        <StateAbbreviationCd>WA</StateAbbreviationCd>
        <ZIPCd>98119</ZIPCd>
      </USAddress>
    </Filer>
    <BusinessOfficerGrp>
      <PersonNm>SONIA HANDFORTH-KOME</PersonNm>
      <PersonTitleTxt>CEO</PersonTitleTxt>
      <PhoneNum>2067833004</PhoneNum>
      <SignatureDt>2023-02-07</SignatureDt>
      <DiscussWithPaidPreparerInd>1</DiscussWithPaidPreparerInd>
    </BusinessOfficerGrp>
    <SigningOfficerGrp>
      <PersonFullName>
        <PersonFirstNm>SONIA</PersonFirstNm>
        <PersonLastNm>HANDFORTH-KOME</PersonLastNm>
      </PersonFullName>
      <SSN>999009999</SSN>
    </SigningOfficerGrp>
    <PreparerPersonGrp>
      <PreparerPersonNm>EMINA O CRESSWELL CPA</PreparerPersonNm>
      <PTIN>P01217304</PTIN>
      <PhoneNum>4252597227</PhoneNum>
      <PreparationDt>2023-02-07</PreparationDt>
    </PreparerPersonGrp>
    <AdditionalFilerInformation>
      <TrustedCustomerGrp>
        <TrustedCustomerCd>0</TrustedCustomerCd>
        <AuthenticationAssuranceLevelCd>AAL1</AuthenticationAssuranceLevelCd>
        <IdentityAssuranceLevelCd>IAL1</IdentityAssuranceLevelCd>
      </TrustedCustomerGrp>
    </AdditionalFilerInformation>
    <TaxYr>2021</TaxYr>
    <BuildTS>2023-03-07 01:45:13Z</BuildTS>
  </ReturnHeader>
  <ReturnData documentCnt="7">
    <IRS990 documentId="RetDoc1038000001" referenceDocumentId="RetDoc1044400001">
      <PrincipalOfficerNm>BRUCE G GRAY</PrincipalOfficerNm>
      <USAddress>
        <AddressLine1Txt>200 WEST THOMAS STREET STE 330</AddressLine1Txt>
        <CityNm>SEATTLE</CityNm>
        <StateAbbreviationCd>WA</StateAbbreviationCd>
        <ZIPCd>98119</ZIPCd>
      </USAddress>
      <GrossReceiptsAmt>4243572</GrossReceiptsAmt>
      <GroupReturnForAffiliatesInd>0</GroupReturnForAffiliatesInd>
      <Organization501c3Ind>X</Organization501c3Ind>
      <WebsiteAddressTxt>WWW.NWRPCA.ORG</WebsiteAddressTxt>
      <TypeOfOrganizationCorpInd>X</TypeOfOrganizationCorpInd>
      <FormationYr>1987</FormationYr>
      <LegalDomicileStateCd>WA</LegalDomicileStateCd>
      <ActivityOrMissionDesc>SUPPORT COMMUNITY-BASED ORGANIZATIONS THAT PROVIDE HEALTH CARE TO UNDESERVED COMMUNITIES.</ActivityOrMissionDesc>
      <VotingMembersGoverningBodyCnt>16</VotingMembersGoverningBodyCnt>
      <VotingMembersIndependentCnt>16</VotingMembersIndependentCnt>
      <TotalEmployeeCnt>24</TotalEmployeeCnt>
      <TotalVolunteersCnt>52</TotalVolunteersCnt>
      <TotalGrossUBIAmt>2500</TotalGrossUBIAmt>
      <NetUnrelatedBusTxblIncmAmt>0</NetUnrelatedBusTxblIncmAmt>
      <PYContributionsGrantsAmt>2131017</PYContributionsGrantsAmt>
      <CYContributionsGrantsAmt>3163014</CYContributionsGrantsAmt>
      <PYProgramServiceRevenueAmt>646865</PYProgramServiceRevenueAmt>
      <CYProgramServiceRevenueAmt>1031925</CYProgramServiceRevenueAmt>
      <PYInvestmentIncomeAmt>28098</PYInvestmentIncomeAmt>
      <CYInvestmentIncomeAmt>13908</CYInvestmentIncomeAmt>
      <PYOtherRevenueAmt>93119</PYOtherRevenueAmt>
      <CYOtherRevenueAmt>29733</CYOtherRevenueAmt>
      <PYTotalRevenueAmt>2899099</PYTotalRevenueAmt>
      <CYTotalRevenueAmt>4238580</CYTotalRevenueAmt>
      <PYGrantsAndSimilarPaidAmt>24468</PYGrantsAndSimilarPaidAmt>
      <CYGrantsAndSimilarPaidAmt>1113890</CYGrantsAndSimilarPaidAmt>
      <PYBenefitsPaidToMembersAmt>0</PYBenefitsPaidToMembersAmt>
      <CYBenefitsPaidToMembersAmt>0</CYBenefitsPaidToMembersAmt>
      <PYSalariesCompEmpBnftPaidAmt>1467800</PYSalariesCompEmpBnftPaidAmt>
      <CYSalariesCompEmpBnftPaidAmt>1673036</CYSalariesCompEmpBnftPaidAmt>
      <PYTotalProfFndrsngExpnsAmt>0</PYTotalProfFndrsngExpnsAmt>
      <CYTotalProfFndrsngExpnsAmt>0</CYTotalProfFndrsngExpnsAmt>
      <CYTotalFundraisingExpenseAmt>106347</CYTotalFundraisingExpenseAmt>
      <PYOtherExpensesAmt>800889</PYOtherExpensesAmt>
      <CYOtherExpensesAmt>1259334</CYOtherExpensesAmt>
      <PYTotalExpensesAmt>2293157</PYTotalExpensesAmt>
      <CYTotalExpensesAmt>4046260</CYTotalExpensesAmt>
      <PYRevenuesLessExpensesAmt>605942</PYRevenuesLessExpensesAmt>
      <CYRevenuesLessExpensesAmt>192320</CYRevenuesLessExpensesAmt>
      <TotalAssetsBOYAmt>2109476</TotalAssetsBOYAmt>
      <TotalAssetsEOYAmt>2762610</TotalAssetsEOYAmt>
      <TotalLiabilitiesBOYAmt>343950</TotalLiabilitiesBOYAmt>
      <TotalLiabilitiesEOYAmt>934480</TotalLiabilitiesEOYAmt>
      <NetAssetsOrFundBalancesBOYAmt>1765526</NetAssetsOrFundBalancesBOYAmt>
      <NetAssetsOrFundBalancesEOYAmt>1828130</NetAssetsOrFundBalancesEOYAmt>
      <InfoInScheduleOPartIIIInd>X</InfoInScheduleOPartIIIInd>
      <MissionDesc>NWRPCA SUPPORTS AND ADVOCATES FOR COMMUNITY-BASED ORGANIZATIONS THAT PROVIDE HIGH-QUALITY, COST EFFECTIVE, COMPREHENSIVE HEALTH CARE SERVICES TO UNDERSERVED COMMUNITES IN THE PACIFIC NORTHWEST, WITHOUT REGARD TO FINANCIAL OR OTHER STATUS.</MissionDesc>
      <SignificantNewProgramSrvcInd>0</SignificantNewProgramSrvcInd>
      <SignificantChangeInd>1</SignificantChangeInd>
      <ExpenseAmt>2886443</ExpenseAmt>
      <GrantAmt>1113890</GrantAmt>
      <RevenueAmt>1029425</RevenueAmt>
      <Desc>NWRPCA ORGANIZES AND HOLDS CONFERENCES, WEBINARS, AND OTHER TRAINING PROGRAMS THAT INCLUDE A WIDE VARIETY OF TOPICS RELEVANT TO COMMUNITY HEALTH CENTERS AND THEIR PARTNERS. NWRPCA PROVIDES TECHNICAL ASSISTANCE AND INFORMATION TO COMMUNITY HEALTH CENTERS AROUND HUMAN RESOURCES, WORKFORCE RECRUITMENT, RETENTION AND MANAGEMENT, FINANCIAL MANAGEMENT, POLICY ANALYSIS AND ADVOCACY, MIGRANT HEALTH SERVICES, SOCIAL DETERMINANTS OF HEALTH, QUALITY IMPROVEMENT, AND OTHER AREAS OF CONCERN OR INTEREST, USING A VARIETY OF DELIVERY MODALITIES INCLUDING A MONTHLY NEWSLETTER, SITE VISITS, INTRODUCTION TO/FACILITATION OF WORK WITH PARTNERS AND SUBJECT MATTER EXPERTS, DATA ANALYSIS AND DATA PRODUCTS SUCH AS A SALARY SURVEY, AND THE AFORMENTIONED TRAINING AND CONFERENCES.</Desc>
      <TotalProgramServiceExpensesAmt>2886443</TotalProgramServiceExpensesAmt>
      <DescribedInSection501c3Ind referenceDocumentId="RetDoc1039100001">1</DescribedInSection501c3Ind>
      <ScheduleBRequiredInd referenceDocumentId="RetDoc1234500001">1</ScheduleBRequiredInd>
      <PoliticalCampaignActyInd>0</PoliticalCampaignActyInd>
      <LobbyingActivitiesInd>0</LobbyingActivitiesInd>
      <SubjectToProxyTaxInd>0</SubjectToProxyTaxInd>
      <DonorAdvisedFundInd referenceDocumentId="RetDoc1040000001">0</DonorAdvisedFundInd>
      <ConservationEasementsInd referenceDocumentId="RetDoc1040000001">0</ConservationEasementsInd>
      <CollectionsOfArtInd referenceDocumentId="RetDoc1040000001">0</CollectionsOfArtInd>
      <CreditCounselingInd referenceDocumentId="RetDoc1040000001">0</CreditCounselingInd>
      <DonorRstrOrQuasiEndowmentsInd>0</DonorRstrOrQuasiEndowmentsInd>
      <ReportLandBuildingEquipmentInd referenceDocumentId="RetDoc1040000001">1</ReportLandBuildingEquipmentInd>
      <ReportInvestmentsOtherSecInd referenceDocumentId="RetDoc1040000001">0</ReportInvestmentsOtherSecInd>
      <ReportProgramRelatedInvstInd referenceDocumentId="RetDoc1040000001">0</ReportProgramRelatedInvstInd>
      <ReportOtherAssetsInd referenceDocumentId="RetDoc1040000001">0</ReportOtherAssetsInd>
      <ReportOtherLiabilitiesInd referenceDocumentId="RetDoc1040000001">0</ReportOtherLiabilitiesInd>
      <IncludeFIN48FootnoteInd referenceDocumentId="RetDoc1040000001">1</IncludeFIN48FootnoteInd>
      <IndependentAuditFinclStmtInd referenceDocumentId="RetDoc1040000001">1</IndependentAuditFinclStmtInd>
      <ConsolidatedAuditFinclStmtInd referenceDocumentId="RetDoc1040000001">0</ConsolidatedAuditFinclStmtInd>
      <SchoolOperatingInd>0</SchoolOperatingInd>
      <ForeignOfficeInd>0</ForeignOfficeInd>
      <ForeignActivitiesInd>0</ForeignActivitiesInd>
      <MoreThan5000KToOrgInd>0</MoreThan5000KToOrgInd>
      <MoreThan5000KToIndividualsInd>0</MoreThan5000KToIndividualsInd>
      <ProfessionalFundraisingInd>0</ProfessionalFundraisingInd>
      <FundraisingActivitiesInd>0</FundraisingActivitiesInd>
      <GamingActivitiesInd>0</GamingActivitiesInd>
      <OperateHospitalInd>0</OperateHospitalInd>
      <GrantsToOrganizationsInd referenceDocumentId="RetDoc1041900001">1</GrantsToOrganizationsInd>
      <GrantsToIndividualsInd referenceDocumentId="RetDoc1041900001">1</GrantsToIndividualsInd>
      <ScheduleJRequiredInd referenceDocumentId="RetDoc1042400001">1</ScheduleJRequiredInd>
      <TaxExemptBondsInd>0</TaxExemptBondsInd>
      <EngagedInExcessBenefitTransInd>0</EngagedInExcessBenefitTransInd>
      <PYExcessBenefitTransInd>0</PYExcessBenefitTransInd>
      <LoanOutstandingInd>0</LoanOutstandingInd>
      <GrantToRelatedPersonInd>0</GrantToRelatedPersonInd>
      <BusinessRlnWithOrgMemInd>0</BusinessRlnWithOrgMemInd>
      <BusinessRlnWithFamMemInd>0</BusinessRlnWithFamMemInd>
      <BusinessRlnWith35CtrlEntInd>0</BusinessRlnWith35CtrlEntInd>
      <DeductibleNonCashContriInd>0</DeductibleNonCashContriInd>
      <DeductibleArtContributionInd>0</DeductibleArtContributionInd>
      <TerminateOperationsInd>0</TerminateOperationsInd>
      <PartialLiquidationInd>0</PartialLiquidationInd>
      <DisregardedEntityInd>0</DisregardedEntityInd>
      <RelatedEntityInd>0</RelatedEntityInd>
      <RelatedOrganizationCtrlEntInd>0</RelatedOrganizationCtrlEntInd>
      <TrnsfrExmptNonChrtblRltdOrgInd>0</TrnsfrExmptNonChrtblRltdOrgInd>
      <ActivitiesConductedPrtshpInd>0</ActivitiesConductedPrtshpInd>
      <ScheduleORequiredInd>1</ScheduleORequiredInd>
      <IRPDocumentCnt>29</IRPDocumentCnt>
      <IRPDocumentW2GCnt>0</IRPDocumentW2GCnt>
      <BackupWthldComplianceInd>1</BackupWthldComplianceInd>
      <EmployeeCnt>24</EmployeeCnt>
      <EmploymentTaxReturnsFiledInd>1</EmploymentTaxReturnsFiledInd>
      <UnrelatedBusIncmOverLimitInd>1</UnrelatedBusIncmOverLimitInd>
      <Form990TFiledInd>1</Form990TFiledInd>
      <ForeignFinancialAccountInd>0</ForeignFinancialAccountInd>
      <ProhibitedTaxShelterTransInd>0</ProhibitedTaxShelterTransInd>
      <TaxablePartyNotificationInd>0</TaxablePartyNotificationInd>
      <NondeductibleContributionsInd>0</NondeductibleContributionsInd>
      <QuidProQuoContributionsInd>0</QuidProQuoContributionsInd>
      <Form8282PropertyDisposedOfInd>0</Form8282PropertyDisposedOfInd>
      <RcvFndsToPayPrsnlBnftCntrctInd>0</RcvFndsToPayPrsnlBnftCntrctInd>
      <PayPremiumsPrsnlBnftCntrctInd>0</PayPremiumsPrsnlBnftCntrctInd>
      <IndoorTanningServicesInd>0</IndoorTanningServicesInd>
      <SubjToTaxRmnrtnExPrchtPymtInd>0</SubjToTaxRmnrtnExPrchtPymtInd>
      <SubjectToExcsTaxNetInvstIncInd>0</SubjectToExcsTaxNetInvstIncInd>
      <InfoInScheduleOPartVIInd>X</InfoInScheduleOPartVIInd>
      <GoverningBodyVotingMembersCnt>16</GoverningBodyVotingMembersCnt>
      <IndependentVotingMemberCnt>16</IndependentVotingMemberCnt>
      <FamilyOrBusinessRlnInd>0</FamilyOrBusinessRlnInd>
      <DelegationOfMgmtDutiesInd>0</DelegationOfMgmtDutiesInd>
      <ChangeToOrgDocumentsInd>0</ChangeToOrgDocumentsInd>
      <MaterialDiversionOrMisuseInd>0</MaterialDiversionOrMisuseInd>
      <MembersOrStockholdersInd>1</MembersOrStockholdersInd>
      <ElectionOfBoardMembersInd>1</ElectionOfBoardMembersInd>
      <DecisionsSubjectToApprovaInd>1</DecisionsSubjectToApprovaInd>
      <MinutesOfGoverningBodyInd>1</MinutesOfGoverningBodyInd>
      <MinutesOfCommitteesInd>1</MinutesOfCommitteesInd>
      <OfficerMailingAddressInd>0</OfficerMailingAddressInd>
      <LocalChaptersInd>0</LocalChaptersInd>
      <Form990ProvidedToGvrnBodyInd>1</Form990ProvidedToGvrnBodyInd>
      <ConflictOfInterestPolicyInd>1</ConflictOfInterestPolicyInd>
      <AnnualDisclosureCoveredPrsnInd>1</AnnualDisclosureCoveredPrsnInd>
      <RegularMonitoringEnfrcInd>1</RegularMonitoringEnfrcInd>
      <WhistleblowerPolicyInd>1</WhistleblowerPolicyInd>
      <DocumentRetentionPolicyInd>1</DocumentRetentionPolicyInd>
      <CompensationProcessCEOInd>1</CompensationProcessCEOInd>
      <CompensationProcessOtherInd>1</CompensationProcessOtherInd>
      <InvestmentInJointVentureInd>0</InvestmentInJointVentureInd>
      <UponRequestInd>X</UponRequestInd>
      <BooksInCareOfDetail>
        <BusinessName>
          <BusinessNameLine1Txt>SONIA HANDFORTH-KOME</BusinessNameLine1Txt>
        </BusinessName>
        <PhoneNum>2067833004</PhoneNum>
        <USAddress>
          <AddressLine1Txt>200 WEST THOMAS STREET</AddressLine1Txt>
          <CityNm>SEATTLE</CityNm>
          <StateAbbreviationCd>WA</StateAbbreviationCd>
          <ZIPCd>98119</ZIPCd>
        </USAddress>
      </BooksInCareOfDetail>
      <Form990PartVIISectionAGrp>
        <PersonNm>BRUCE GRAY</PersonNm>
        <TitleTxt>CEO</TitleTxt>
        <AverageHoursPerWeekRt>40.00</AverageHoursPerWeekRt>
        <OfficerInd>X</OfficerInd>
        <ReportableCompFromOrgAmt>217338</ReportableCompFromOrgAmt>
        <ReportableCompFromRltdOrgAmt>0</ReportableCompFromRltdOrgAmt>
        <OtherCompensationAmt>17229</OtherCompensationAmt>
      </Form990PartVIISectionAGrp>
      <Form990PartVIISectionAGrp>
        <PersonNm>SADIE AGURKIS</PersonNm>
        <TitleTxt>COO</TitleTxt>
        <AverageHoursPerWeekRt>40.00</AverageHoursPerWeekRt>
        <OfficerInd>X</OfficerInd>
        <ReportableCompFromOrgAmt>114855</ReportableCompFromOrgAmt>
        <ReportableCompFromRltdOrgAmt>0</ReportableCompFromRltdOrgAmt>
        <OtherCompensationAmt>4036</OtherCompensationAmt>
      </Form990PartVIISectionAGrp>
      <Form990PartVIISectionAGrp>
        <PersonNm>SONIA HANDFORTH-KOME</PersonNm>
        <TitleTxt>CFO</TitleTxt>
        <AverageHoursPerWeekRt>40.00</AverageHoursPerWeekRt>
        <OfficerInd>X</OfficerInd>
        <ReportableCompFromOrgAmt>109046</ReportableCompFromOrgAmt>
        <ReportableCompFromRltdOrgAmt>0</ReportableCompFromRltdOrgAmt>
        <OtherCompensationAmt>5950</OtherCompensationAmt>
      </Form990PartVIISectionAGrp>
      <Form990PartVIISectionAGrp>
        <PersonNm>JESUS HERNANDEZ</PersonNm>
        <TitleTxt>BOARD PRESIDENT</TitleTxt>
        <AverageHoursPerWeekRt>2.00</AverageHoursPerWeekRt>
        <IndividualTrusteeOrDirectorInd>X</IndividualTrusteeOrDirectorInd>
        <OfficerInd>X</OfficerInd>
        <ReportableCompFromOrgAmt>0</ReportableCompFromOrgAmt>
        <ReportableCompFromRltdOrgAmt>0</ReportableCompFromRltdOrgAmt>
        <OtherCompensationAmt>0</OtherCompensationAmt>
      </Form990PartVIISectionAGrp>
      <Form990PartVIISectionAGrp>
        <PersonNm>TAWNY BUCK</PersonNm>
        <TitleTxt>BOARD VICE CHAIR</TitleTxt>
        <AverageHoursPerWeekRt>1.00</AverageHoursPerWeekRt>
        <IndividualTrusteeOrDirectorInd>X</IndividualTrusteeOrDirectorInd>
        <OfficerInd>X</OfficerInd>
        <ReportableCompFromOrgAmt>0</ReportableCompFromOrgAmt>
        <ReportableCompFromRltdOrgAmt>0</ReportableCompFromRltdOrgAmt>
        <OtherCompensationAmt>0</OtherCompensationAmt>
      </Form990PartVIISectionAGrp>
      <Form990PartVIISectionAGrp>
        <PersonNm>MIKE BAKER</PersonNm>
        <TitleTxt>TREASURER</TitleTxt>
        <AverageHoursPerWeekRt>1.00</AverageHoursPerWeekRt>
        <IndividualTrusteeOrDirectorInd>X</IndividualTrusteeOrDirectorInd>
        <OfficerInd>X</OfficerInd>
        <ReportableCompFromOrgAmt>0</ReportableCompFromOrgAmt>
        <ReportableCompFromRltdOrgAmt>0</ReportableCompFromRltdOrgAmt>
        <OtherCompensationAmt>0</OtherCompensationAmt>
      </Form990PartVIISectionAGrp>
      <Form990PartVIISectionAGrp>
        <PersonNm>LINDA MAXON</PersonNm>
        <TitleTxt>BOARD SECRETARY</TitleTxt>
        <AverageHoursPerWeekRt>1.00</AverageHoursPerWeekRt>
        <IndividualTrusteeOrDirectorInd>X</IndividualTrusteeOrDirectorInd>
        <OfficerInd>X</OfficerInd>
        <ReportableCompFromOrgAmt>0</ReportableCompFromOrgAmt>
        <ReportableCompFromRltdOrgAmt>0</ReportableCompFromRltdOrgAmt>
        <OtherCompensationAmt>0</OtherCompensationAmt>
      </Form990PartVIISectionAGrp>
      <Form990PartVIISectionAGrp>
        <PersonNm>MINDY STOSICH-BENEDETTI</PersonNm>
        <TitleTxt>DIRECTOR</TitleTxt>
        <AverageHoursPerWeekRt>1.00</AverageHoursPerWeekRt>
        <IndividualTrusteeOrDirectorInd>X</IndividualTrusteeOrDirectorInd>
        <ReportableCompFromOrgAmt>0</ReportableCompFromOrgAmt>
        <ReportableCompFromRltdOrgAmt>0</ReportableCompFromRltdOrgAmt>
        <OtherCompensationAmt>0</OtherCompensationAmt>
      </Form990PartVIISectionAGrp>
      <Form990PartVIISectionAGrp>
        <PersonNm>HEIDI HART</PersonNm>
        <TitleTxt>DIRECTOR</TitleTxt>
        <AverageHoursPerWeekRt>1.00</AverageHoursPerWeekRt>
        <IndividualTrusteeOrDirectorInd>X</IndividualTrusteeOrDirectorInd>
        <ReportableCompFromOrgAmt>0</ReportableCompFromOrgAmt>
        <ReportableCompFromRltdOrgAmt>0</ReportableCompFromRltdOrgAmt>
        <OtherCompensationAmt>0</OtherCompensationAmt>
      </Form990PartVIISectionAGrp>
      <Form990PartVIISectionAGrp>
        <PersonNm>CRAIG AMBROSIANI</PersonNm>
        <TitleTxt>DIRECTOR</TitleTxt>
        <AverageHoursPerWeekRt>1.00</AverageHoursPerWeekRt>
        <IndividualTrusteeOrDirectorInd>X</IndividualTrusteeOrDirectorInd>
        <ReportableCompFromOrgAmt>0</ReportableCompFromOrgAmt>
        <ReportableCompFromRltdOrgAmt>0</ReportableCompFromRltdOrgAmt>
        <OtherCompensationAmt>0</OtherCompensationAmt>
      </Form990PartVIISectionAGrp>
      <Form990PartVIISectionAGrp>
        <PersonNm>ERIC GETTIS</PersonNm>
        <TitleTxt>DIRECTOR</TitleTxt>
        <AverageHoursPerWeekRt>1.00</AverageHoursPerWeekRt>
        <IndividualTrusteeOrDirectorInd>X</IndividualTrusteeOrDirectorInd>
        <ReportableCompFromOrgAmt>0</ReportableCompFromOrgAmt>
        <ReportableCompFromRltdOrgAmt>0</ReportableCompFromRltdOrgAmt>
        <OtherCompensationAmt>0</OtherCompensationAmt>
      </Form990PartVIISectionAGrp>
      <Form990PartVIISectionAGrp>
        <PersonNm>KEVIN MUNSON</PersonNm>
        <TitleTxt>DIRECTOR</TitleTxt>
        <AverageHoursPerWeekRt>1.00</AverageHoursPerWeekRt>
        <IndividualTrusteeOrDirectorInd>X</IndividualTrusteeOrDirectorInd>
        <ReportableCompFromOrgAmt>0</ReportableCompFromOrgAmt>
        <ReportableCompFromRltdOrgAmt>0</ReportableCompFromRltdOrgAmt>
        <OtherCompensationAmt>0</OtherCompensationAmt>
      </Form990PartVIISectionAGrp>
      <Form990PartVIISectionAGrp>
        <PersonNm>GIL MUNOZ</PersonNm>
        <TitleTxt>DIRECTOR</TitleTxt>
        <AverageHoursPerWeekRt>1.00</AverageHoursPerWeekRt>
        <IndividualTrusteeOrDirectorInd>X</IndividualTrusteeOrDirectorInd>
        <ReportableCompFromOrgAmt>0</ReportableCompFromOrgAmt>
        <ReportableCompFromRltdOrgAmt>0</ReportableCompFromRltdOrgAmt>
        <OtherCompensationAmt>0</OtherCompensationAmt>
      </Form990PartVIISectionAGrp>
      <Form990PartVIISectionAGrp>
        <PersonNm>ESTHER LUCERO</PersonNm>
        <TitleTxt>DIRECTOR</TitleTxt>
        <AverageHoursPerWeekRt>1.00</AverageHoursPerWeekRt>
        <IndividualTrusteeOrDirectorInd>X</IndividualTrusteeOrDirectorInd>
        <ReportableCompFromOrgAmt>0</ReportableCompFromOrgAmt>
        <ReportableCompFromRltdOrgAmt>0</ReportableCompFromRltdOrgAmt>
        <OtherCompensationAmt>0</OtherCompensationAmt>
      </Form990PartVIISectionAGrp>
      <Form990PartVIISectionAGrp>
        <PersonNm>JIM COFFEE</PersonNm>
        <TitleTxt>DIRECTOR</TitleTxt>
        <AverageHoursPerWeekRt>1.00</AverageHoursPerWeekRt>
        <IndividualTrusteeOrDirectorInd>X</IndividualTrusteeOrDirectorInd>
        <ReportableCompFromOrgAmt>0</ReportableCompFromOrgAmt>
        <ReportableCompFromRltdOrgAmt>0</ReportableCompFromRltdOrgAmt>
        <OtherCompensationAmt>0</OtherCompensationAmt>
      </Form990PartVIISectionAGrp>
      <Form990PartVIISectionAGrp>
        <PersonNm>PATRICK LUEDTKE</PersonNm>
        <TitleTxt>DIRECTOR</TitleTxt>
        <AverageHoursPerWeekRt>1.00</AverageHoursPerWeekRt>
        <IndividualTrusteeOrDirectorInd>X</IndividualTrusteeOrDirectorInd>
        <ReportableCompFromOrgAmt>0</ReportableCompFromOrgAmt>
        <ReportableCompFromRltdOrgAmt>0</ReportableCompFromRltdOrgAmt>
        <OtherCompensationAmt>0</OtherCompensationAmt>
      </Form990PartVIISectionAGrp>
      <Form990PartVIISectionAGrp>
        <PersonNm>AARON HOUSTON</PersonNm>
        <TitleTxt>DIRECTOR</TitleTxt>
        <AverageHoursPerWeekRt>1.00</AverageHoursPerWeekRt>
        <IndividualTrusteeOrDirectorInd>X</IndividualTrusteeOrDirectorInd>
        <ReportableCompFromOrgAmt>0</ReportableCompFromOrgAmt>
        <ReportableCompFromRltdOrgAmt>0</ReportableCompFromRltdOrgAmt>
        <OtherCompensationAmt>0</OtherCompensationAmt>
      </Form990PartVIISectionAGrp>
      <Form990PartVIISectionAGrp>
        <PersonNm>WILLIAM NORTH</PersonNm>
        <TitleTxt>DIRECTOR</TitleTxt>
        <AverageHoursPerWeekRt>1.00</AverageHoursPerWeekRt>
        <IndividualTrusteeOrDirectorInd>X</IndividualTrusteeOrDirectorInd>
        <ReportableCompFromOrgAmt>0</ReportableCompFromOrgAmt>
        <ReportableCompFromRltdOrgAmt>0</ReportableCompFromRltdOrgAmt>
        <OtherCompensationAmt>0</OtherCompensationAmt>
      </Form990PartVIISectionAGrp>
      <Form990PartVIISectionAGrp>
        <PersonNm>JOHN BROWNE</PersonNm>
        <TitleTxt>DIRECTOR</TitleTxt>
        <AverageHoursPerWeekRt>1.00</AverageHoursPerWeekRt>
        <IndividualTrusteeOrDirectorInd>X</IndividualTrusteeOrDirectorInd>
        <ReportableCompFromOrgAmt>0</ReportableCompFromOrgAmt>
        <ReportableCompFromRltdOrgAmt>0</ReportableCompFromRltdOrgAmt>
        <OtherCompensationAmt>0</OtherCompensationAmt>
      </Form990PartVIISectionAGrp>
      <Form990PartVIISectionAGrp>
        <PersonNm>CHARLA DEHATE</PersonNm>
        <TitleTxt>DIRECTOR (THRU 6/22)</TitleTxt>
        <AverageHoursPerWeekRt>1.00</AverageHoursPerWeekRt>
        <IndividualTrusteeOrDirectorInd>X</IndividualTrusteeOrDirectorInd>
        <ReportableCompFromOrgAmt>0</ReportableCompFromOrgAmt>
        <ReportableCompFromRltdOrgAmt>0</ReportableCompFromRltdOrgAmt>
        <OtherCompensationAmt>0</OtherCompensationAmt>
      </Form990PartVIISectionAGrp>
      <Form990PartVIISectionAGrp>
        <PersonNm>SHEILA BERSCHAUER</PersonNm>
        <TitleTxt>DIRECTOR (THRU 6/22)</TitleTxt>
        <AverageHoursPerWeekRt>1.00</AverageHoursPerWeekRt>
        <IndividualTrusteeOrDirectorInd>X</IndividualTrusteeOrDirectorInd>
        <ReportableCompFromOrgAmt>0</ReportableCompFromOrgAmt>
        <ReportableCompFromRltdOrgAmt>0</ReportableCompFromRltdOrgAmt>
        <OtherCompensationAmt>0</OtherCompensationAmt>
      </Form990PartVIISectionAGrp>
      <TotalReportableCompFromOrgAmt>441239</TotalReportableCompFromOrgAmt>
      <TotReportableCompRltdOrgAmt>0</TotReportableCompRltdOrgAmt>
      <TotalOtherCompensationAmt>27215</TotalOtherCompensationAmt>
      <IndivRcvdGreaterThan100KCnt>3</IndivRcvdGreaterThan100KCnt>
      <FormerOfcrEmployeesListedInd>0</FormerOfcrEmployeesListedInd>
      <TotalCompGreaterThan150KInd>1</TotalCompGreaterThan150KInd>
      <CompensationFromOtherSrcsInd>0</CompensationFromOtherSrcsInd>
      <CntrctRcvdGreaterThan100KCnt>0</CntrctRcvdGreaterThan100KCnt>
      <GovernmentGrantsAmt>1961260</GovernmentGrantsAmt>
      <AllOtherContributionsAmt>1201754</AllOtherContributionsAmt>
      <TotalContributionsAmt>3163014</TotalContributionsAmt>
      <ProgramServiceRevenueGrp>
        <Desc>CONFERENCES</Desc>
        <BusinessCd>611430</BusinessCd>
        <TotalRevenueColumnAmt>835915</TotalRevenueColumnAmt>
        <RelatedOrExemptFuncIncomeAmt>835915</RelatedOrExemptFuncIncomeAmt>
      </ProgramServiceRevenueGrp>
      <ProgramServiceRevenueGrp>
        <Desc>MEMBERSHIP DUES</Desc>
        <BusinessCd>611430</BusinessCd>
        <TotalRevenueColumnAmt>193510</TotalRevenueColumnAmt>
        <RelatedOrExemptFuncIncomeAmt>193510</RelatedOrExemptFuncIncomeAmt>
      </ProgramServiceRevenueGrp>
      <ProgramServiceRevenueGrp>
        <Desc>CONFERENCE BROCHURE</Desc>
        <BusinessCd>541800</BusinessCd>
        <TotalRevenueColumnAmt>2500</TotalRevenueColumnAmt>
        <UnrelatedBusinessRevenueAmt>2500</UnrelatedBusinessRevenueAmt>
      </ProgramServiceRevenueGrp>
      <TotalProgramServiceRevenueAmt>1031925</TotalProgramServiceRevenueAmt>
      <InvestmentIncomeGrp>
        <TotalRevenueColumnAmt>18900</TotalRevenueColumnAmt>
        <ExclusionAmt>18900</ExclusionAmt>
      </InvestmentIncomeGrp>
      <LessCostOthBasisSalesExpnssGrp>
        <OtherAmt>4992</OtherAmt>
      </LessCostOthBasisSalesExpnssGrp>
      <GainOrLossGrp>
        <OtherAmt>-4992</OtherAmt>
      </GainOrLossGrp>
      <NetGainOrLossInvestmentsGrp>
        <TotalRevenueColumnAmt>-4992</TotalRevenueColumnAmt>
        <ExclusionAmt>-4992</ExclusionAmt>
      </NetGainOrLossInvestmentsGrp>
      <OtherRevenueMiscGrp>
        <Desc>MISCELLANEOUS REVENUE</Desc>
        <BusinessCd>900099</BusinessCd>
        <TotalRevenueColumnAmt>113680</TotalRevenueColumnAmt>
        <ExclusionAmt>113680</ExclusionAmt>
      </OtherRevenueMiscGrp>
      <OtherRevenueMiscGrp>
        <Desc>SALARY SURVEY</Desc>
        <BusinessCd>900099</BusinessCd>
        <TotalRevenueColumnAmt>4250</TotalRevenueColumnAmt>
        <ExclusionAmt>4250</ExclusionAmt>
      </OtherRevenueMiscGrp>
      <OtherRevenueMiscGrp>
        <Desc>INVESTMENT IN EHCI</Desc>
        <BusinessCd>900099</BusinessCd>
        <TotalRevenueColumnAmt>-88197</TotalRevenueColumnAmt>
        <ExclusionAmt>-88197</ExclusionAmt>
      </OtherRevenueMiscGrp>
      <OtherRevenueTotalAmt>29733</OtherRevenueTotalAmt>
      <TotalRevenueGrp>
        <TotalRevenueColumnAmt>4238580</TotalRevenueColumnAmt>
        <RelatedOrExemptFuncIncomeAmt>1029425</RelatedOrExemptFuncIncomeAmt>
        <UnrelatedBusinessRevenueAmt>2500</UnrelatedBusinessRevenueAmt>
        <ExclusionAmt>43641</ExclusionAmt>
      </TotalRevenueGrp>
      <InfoInScheduleOPartIXInd>X</InfoInScheduleOPartIXInd>
      <GrantsToDomesticOrgsGrp>
        <TotalAmt>796079</TotalAmt>
        <ProgramServicesAmt>796079</ProgramServicesAmt>
      </GrantsToDomesticOrgsGrp>
      <GrantsToDomesticIndividualsGrp>
        <TotalAmt>317811</TotalAmt>
        <ProgramServicesAmt>317811</ProgramServicesAmt>
      </GrantsToDomesticIndividualsGrp>
      <CompCurrentOfcrDirectorsGrp>
        <TotalAmt>426569</TotalAmt>
        <ProgramServicesAmt>251209</ProgramServicesAmt>
        <ManagementAndGeneralAmt>151754</ManagementAndGeneralAmt>
        <FundraisingAmt>23606</FundraisingAmt>
      </CompCurrentOfcrDirectorsGrp>
      <OtherSalariesAndWagesGrp>
        <TotalAmt>1048958</TotalAmt>
        <ProgramServicesAmt>617738</ProgramServicesAmt>
        <ManagementAndGeneralAmt>373172</ManagementAndGeneralAmt>
        <FundraisingAmt>58048</FundraisingAmt>
      </OtherSalariesAndWagesGrp>
      <PensionPlanContributionsGrp>
        <TotalAmt>3601</TotalAmt>
        <ProgramServicesAmt>2121</ProgramServicesAmt>
        <ManagementAndGeneralAmt>1281</ManagementAndGeneralAmt>
        <FundraisingAmt>199</FundraisingAmt>
      </PensionPlanContributionsGrp>
      <OtherEmployeeBenefitsGrp>
        <TotalAmt>84371</TotalAmt>
        <ProgramServicesAmt>49687</ProgramServicesAmt>
        <ManagementAndGeneralAmt>30015</ManagementAndGeneralAmt>
        <FundraisingAmt>4669</FundraisingAmt>
      </OtherEmployeeBenefitsGrp>
      <PayrollTaxesGrp>
        <TotalAmt>109537</TotalAmt>
        <ProgramServicesAmt>68288</ProgramServicesAmt>
        <ManagementAndGeneralAmt>34976</ManagementAndGeneralAmt>
        <FundraisingAmt>6273</FundraisingAmt>
      </PayrollTaxesGrp>
      <FeesForServicesLegalGrp>
        <TotalAmt>20317</TotalAmt>
        <ManagementAndGeneralAmt>20317</ManagementAndGeneralAmt>
      </FeesForServicesLegalGrp>
      <FeesForServicesAccountingGrp>
        <TotalAmt>26513</TotalAmt>
        <ManagementAndGeneralAmt>26513</ManagementAndGeneralAmt>
      </FeesForServicesAccountingGrp>
      <FeesForServicesOtherGrp>
        <TotalAmt>457383</TotalAmt>
        <ProgramServicesAmt>296454</ProgramServicesAmt>
        <ManagementAndGeneralAmt>152221</ManagementAndGeneralAmt>
        <FundraisingAmt>8708</FundraisingAmt>
      </FeesForServicesOtherGrp>
      <AdvertisingGrp>
        <TotalAmt>43533</TotalAmt>
        <ProgramServicesAmt>12876</ProgramServicesAmt>
        <ManagementAndGeneralAmt>27789</ManagementAndGeneralAmt>
        <FundraisingAmt>2868</FundraisingAmt>
      </AdvertisingGrp>
      <OfficeExpensesGrp>
        <TotalAmt>43330</TotalAmt>
        <ProgramServicesAmt>17890</ProgramServicesAmt>
        <ManagementAndGeneralAmt>23464</ManagementAndGeneralAmt>
        <FundraisingAmt>1976</FundraisingAmt>
      </OfficeExpensesGrp>
      <OccupancyGrp>
        <TotalAmt>159405</TotalAmt>
        <ProgramServicesAmt>21816</ProgramServicesAmt>
        <ManagementAndGeneralAmt>137589</ManagementAndGeneralAmt>
      </OccupancyGrp>
      <TravelGrp>
        <TotalAmt>17928</TotalAmt>
        <ProgramServicesAmt>7807</ProgramServicesAmt>
        <ManagementAndGeneralAmt>10121</ManagementAndGeneralAmt>
      </TravelGrp>
      <ConferencesMeetingsGrp>
        <TotalAmt>355114</TotalAmt>
        <ProgramServicesAmt>339052</ProgramServicesAmt>
        <ManagementAndGeneralAmt>16062</ManagementAndGeneralAmt>
      </ConferencesMeetingsGrp>
      <InterestGrp>
        <TotalAmt>706</TotalAmt>
        <ManagementAndGeneralAmt>706</ManagementAndGeneralAmt>
      </InterestGrp>
      <DepreciationDepletionGrp>
        <TotalAmt>13805</TotalAmt>
        <ProgramServicesAmt>4070</ProgramServicesAmt>
        <ManagementAndGeneralAmt>9735</ManagementAndGeneralAmt>
      </DepreciationDepletionGrp>
      <InsuranceGrp>
        <TotalAmt>12501</TotalAmt>
        <ManagementAndGeneralAmt>12501</ManagementAndGeneralAmt>
      </InsuranceGrp>
      <OtherExpensesGrp>
        <Desc>TAXES, LICENSES, FEES</Desc>
        <TotalAmt>68531</TotalAmt>
        <ProgramServicesAmt>59867</ProgramServicesAmt>
        <ManagementAndGeneralAmt>8664</ManagementAndGeneralAmt>
      </OtherExpensesGrp>
      <OtherExpensesGrp>
        <Desc>SUBSCRIPTIONS</Desc>
        <TotalAmt>17334</TotalAmt>
        <ProgramServicesAmt>13754</ProgramServicesAmt>
        <ManagementAndGeneralAmt>3580</ManagementAndGeneralAmt>
      </OtherExpensesGrp>
      <OtherExpensesGrp>
        <Desc>RECOGNITION &amp; AWARDS</Desc>
        <TotalAmt>17145</TotalAmt>
        <ProgramServicesAmt>9924</ProgramServicesAmt>
        <ManagementAndGeneralAmt>7221</ManagementAndGeneralAmt>
      </OtherExpensesGrp>
      <OtherExpensesGrp>
        <Desc>EQUIPMENT &amp; MAINTENANCE</Desc>
        <TotalAmt>5789</TotalAmt>
        <ManagementAndGeneralAmt>5789</ManagementAndGeneralAmt>
      </OtherExpensesGrp>
      <TotalFunctionalExpensesGrp>
        <TotalAmt>4046260</TotalAmt>
        <ProgramServicesAmt>2886443</ProgramServicesAmt>
        <ManagementAndGeneralAmt>1053470</ManagementAndGeneralAmt>
        <FundraisingAmt>106347</FundraisingAmt>
      </TotalFunctionalExpensesGrp>
      <CashNonInterestBearingGrp>
        <BOYAmt>951341</BOYAmt>
        <EOYAmt>1522240</EOYAmt>
      </CashNonInterestBearingGrp>
      <SavingsAndTempCashInvstGrp>
        <BOYAmt>973014</BOYAmt>
        <EOYAmt>857111</EOYAmt>
      </SavingsAndTempCashInvstGrp>
      <AccountsReceivableGrp>
        <BOYAmt>17190</BOYAmt>
        <EOYAmt>251315</EOYAmt>
      </AccountsReceivableGrp>
      <PrepaidExpensesDefrdChargesGrp>
        <BOYAmt>79858</BOYAmt>
        <EOYAmt>117911</EOYAmt>
      </PrepaidExpensesDefrdChargesGrp>
      <LandBldgEquipCostOrOtherBssAmt>162484</LandBldgEquipCostOrOtherBssAmt>
      <LandBldgEquipAccumDeprecAmt>148451</LandBldgEquipAccumDeprecAmt>
      <LandBldgEquipBasisNetGrp>
        <BOYAmt>32830</BOYAmt>
        <EOYAmt>14033</EOYAmt>
      </LandBldgEquipBasisNetGrp>
      <InvestmentsProgramRelatedGrp>
        <BOYAmt>43346</BOYAmt>
        <EOYAmt>0</EOYAmt>
      </InvestmentsProgramRelatedGrp>
      <OtherAssetsTotalGrp>
        <BOYAmt>11897</BOYAmt>
        <EOYAmt>0</EOYAmt>
      </OtherAssetsTotalGrp>
      <TotalAssetsGrp>
        <BOYAmt>2109476</BOYAmt>
        <EOYAmt>2762610</EOYAmt>
      </TotalAssetsGrp>
      <AccountsPayableAccrExpnssGrp>
        <BOYAmt>186233</BOYAmt>
        <EOYAmt>608638</EOYAmt>
      </AccountsPayableAccrExpnssGrp>
      <DeferredRevenueGrp>
        <BOYAmt>135533</BOYAmt>
        <EOYAmt>310992</EOYAmt>
      </DeferredRevenueGrp>
      <MortgNotesPyblScrdInvstPropGrp>
        <BOYAmt>22184</BOYAmt>
        <EOYAmt>14850</EOYAmt>
      </MortgNotesPyblScrdInvstPropGrp>
      <TotalLiabilitiesGrp>
        <BOYAmt>343950</BOYAmt>
        <EOYAmt>934480</EOYAmt>
      </TotalLiabilitiesGrp>
      <OrganizationFollowsFASB117Ind>X</OrganizationFollowsFASB117Ind>
      <NoDonorRestrictionNetAssetsGrp>
        <BOYAmt>1622669</BOYAmt>
        <EOYAmt>1828130</EOYAmt>
      </NoDonorRestrictionNetAssetsGrp>
      <DonorRestrictionNetAssetsGrp>
        <BOYAmt>142857</BOYAmt>
        <EOYAmt>0</EOYAmt>
      </DonorRestrictionNetAssetsGrp>
      <TotalNetAssetsFundBalanceGrp>
        <BOYAmt>1765526</BOYAmt>
        <EOYAmt>1828130</EOYAmt>
      </TotalNetAssetsFundBalanceGrp>
      <TotLiabNetAssetsFundBalanceGrp>
        <BOYAmt>2109476</BOYAmt>
        <EOYAmt>2762610</EOYAmt>
      </TotLiabNetAssetsFundBalanceGrp>
      <ReconcilationRevenueExpnssAmt>192320</ReconcilationRevenueExpnssAmt>
      <NetUnrlzdGainsLossesInvstAmt>-129716</NetUnrlzdGainsLossesInvstAmt>
      <OtherChangesInNetAssetsAmt>0</OtherChangesInNetAssetsAmt>
      <MethodOfAccountingAccrualInd>X</MethodOfAccountingAccrualInd>
      <AccountantCompileOrReviewInd>0</AccountantCompileOrReviewInd>
      <FSAuditedInd>1</FSAuditedInd>
      <FSAuditedBasisGrp>
        <SeparateBasisFinclStmtInd>X</SeparateBasisFinclStmtInd>
      </FSAuditedBasisGrp>
      <AuditCommitteeInd>1</AuditCommitteeInd>
      <FederalGrantAuditRequiredInd>1</FederalGrantAuditRequiredInd>
      <FederalGrantAuditPerformedInd>1</FederalGrantAuditPerformedInd>
    </IRS990>
    <IRS990ScheduleA documentId="RetDoc1039100001">
      <PublicOrganization170Ind>X</PublicOrganization170Ind>
      <GiftsGrantsContriRcvd170Grp>
        <CurrentTaxYearMinus4YearsAmt>1339002</CurrentTaxYearMinus4YearsAmt>
        <CurrentTaxYearMinus3YearsAmt>1467503</CurrentTaxYearMinus3YearsAmt>
        <CurrentTaxYearMinus2YearsAmt>1463032</CurrentTaxYearMinus2YearsAmt>
        <CurrentTaxYearMinus1YearAmt>2131017</CurrentTaxYearMinus1YearAmt>
        <CurrentTaxYearAmt>3163014</CurrentTaxYearAmt>
        <TotalAmt>9563568</TotalAmt>
      </GiftsGrantsContriRcvd170Grp>
      <TotalCalendarYear170Grp>
        <CurrentTaxYearMinus4YearsAmt>1339002</CurrentTaxYearMinus4YearsAmt>
        <CurrentTaxYearMinus3YearsAmt>1467503</CurrentTaxYearMinus3YearsAmt>
        <CurrentTaxYearMinus2YearsAmt>1463032</CurrentTaxYearMinus2YearsAmt>
        <CurrentTaxYearMinus1YearAmt>2131017</CurrentTaxYearMinus1YearAmt>
        <CurrentTaxYearAmt>3163014</CurrentTaxYearAmt>
        <TotalAmt>9563568</TotalAmt>
      </TotalCalendarYear170Grp>
      <SubstantialContributorsTotAmt>299968</SubstantialContributorsTotAmt>
      <PublicSupportTotal170Amt>9263600</PublicSupportTotal170Amt>
      <GrossInvestmentIncome170Grp>
        <CurrentTaxYearMinus4YearsAmt>22771</CurrentTaxYearMinus4YearsAmt>
        <CurrentTaxYearMinus3YearsAmt>25143</CurrentTaxYearMinus3YearsAmt>
        <CurrentTaxYearMinus2YearsAmt>23102</CurrentTaxYearMinus2YearsAmt>
        <CurrentTaxYearMinus1YearAmt>18627</CurrentTaxYearMinus1YearAmt>
        <CurrentTaxYearAmt>18900</CurrentTaxYearAmt>
        <TotalAmt>108543</TotalAmt>
      </GrossInvestmentIncome170Grp>
      <UnrelatedBusinessNetIncm170Grp>
        <CurrentTaxYearMinus4YearsAmt>19780</CurrentTaxYearMinus4YearsAmt>
        <CurrentTaxYearMinus3YearsAmt>6838</CurrentTaxYearMinus3YearsAmt>
        <CurrentTaxYearMinus2YearsAmt>1384</CurrentTaxYearMinus2YearsAmt>
        <CurrentTaxYearMinus1YearAmt>1495</CurrentTaxYearMinus1YearAmt>
        <CurrentTaxYearAmt>0</CurrentTaxYearAmt>
        <TotalAmt>29497</TotalAmt>
      </UnrelatedBusinessNetIncm170Grp>
      <OtherIncome170Grp>
        <CurrentTaxYearMinus4YearsAmt>50071</CurrentTaxYearMinus4YearsAmt>
        <CurrentTaxYearMinus3YearsAmt>84202</CurrentTaxYearMinus3YearsAmt>
        <CurrentTaxYearMinus2YearsAmt>42860</CurrentTaxYearMinus2YearsAmt>
        <CurrentTaxYearMinus1YearAmt>93119</CurrentTaxYearMinus1YearAmt>
        <CurrentTaxYearAmt>29733</CurrentTaxYearAmt>
        <TotalAmt>299985</TotalAmt>
      </OtherIncome170Grp>
      <TotalSupportAmt>10001593</TotalSupportAmt>
      <GrossReceiptsRltdActivitiesAmt>4830493</GrossReceiptsRltdActivitiesAmt>
      <PublicSupportCY170Pct>0.92620</PublicSupportCY170Pct>
      <PublicSupportPY170Pct>0.92740</PublicSupportPY170Pct>
      <ThirtyThrPctSuprtTestsCY170Ind>X</ThirtyThrPctSuprtTestsCY170Ind>
    </IRS990ScheduleA>
    <IRS990ScheduleB documentId="RetDoc1234500001">
      <ContributorInformationGrp>
        <ContributorNum>RESTRICTED</ContributorNum>
        <ContributorBusinessName>
          <BusinessNameLine1>RESTRICTED</BusinessNameLine1>
        </ContributorBusinessName>
        <ContributorUSAddress>
          <AddressLine1>RESTRICTED</AddressLine1>
          <AddressLine2>RESTRICTED</AddressLine2>
          <City>RESTRICTED</City>
          <State>RESTRICTED</State>
          <ZIPCode>RESTRICTED</ZIPCode>
        </ContributorUSAddress>
        <TotalContributionsAmt>RESTRICTED</TotalContributionsAmt>
      </ContributorInformationGrp>
    </IRS990ScheduleB>
    <IRS990ScheduleD documentId="RetDoc1040000001">
      <LeaseholdImprovementsGrp>
        <OtherCostOrOtherBasisAmt>125876</OtherCostOrOtherBasisAmt>
        <DepreciationAmt>125876</DepreciationAmt>
        <BookValueAmt>0</BookValueAmt>
      </LeaseholdImprovementsGrp>
      <OtherLandBuildingsGrp>
        <OtherCostOrOtherBasisAmt>36608</OtherCostOrOtherBasisAmt>
        <DepreciationAmt>22575</DepreciationAmt>
        <BookValueAmt>14033</BookValueAmt>
      </OtherLandBuildingsGrp>
      <TotalBookValueLandBuildingsAmt>14033</TotalBookValueLandBuildingsAmt>
      <FootnoteTextInd>X</FootnoteTextInd>
      <TotalRevEtcAuditedFinclStmtAmt>4110410</TotalRevEtcAuditedFinclStmtAmt>
      <NetUnrealizedGainsInvstAmt>-129716</NetUnrealizedGainsInvstAmt>
      <OtherRevenueAmt>4992</OtherRevenueAmt>
      <RevenueNotReportedAmt>-124724</RevenueNotReportedAmt>
      <RevenueSubtotalAmt>4235134</RevenueSubtotalAmt>
      <OtherRevenuesNotIncludedAmt>3446</OtherRevenuesNotIncludedAmt>
      <RevenueNotReportedFinclStmtAmt>3446</RevenueNotReportedFinclStmtAmt>
      <TotalRevenuePerForm990Amt>4238580</TotalRevenuePerForm990Amt>
      <TotExpnsEtcAuditedFinclStmtAmt>4047806</TotExpnsEtcAuditedFinclStmtAmt>
      <OtherExpensesIncludedAmt>4992</OtherExpensesIncludedAmt>
      <ExpensesNotReportedAmt>4992</ExpensesNotReportedAmt>
      <ExpensesSubtotalAmt>4042814</ExpensesSubtotalAmt>
      <OtherExpensesNotIncludedAmt>3446</OtherExpensesNotIncludedAmt>
      <ExpensesNotRptFinclStmtAmt>3446</ExpensesNotRptFinclStmtAmt>
      <TotalExpensesPerForm990Amt>4046260</TotalExpensesPerForm990Amt>
      <SupplementalInformationDetail>
        <FormAndLineReferenceDesc>PART X, LINE 2:</FormAndLineReferenceDesc>
        <ExplanationTxt>THE INTERNAL REVENUE SERVICE HAS DETERMINED THAT THE ORGANIZATION IS A TAX-EXEMPT ORGANIZATION UNDER SECTION 501(C)(3) OF THE INTERNAL REVENUE CODE. ACCOUNTING PRINCIPLES GENERALLY ACCEPTED IN THE UNITED STATES OF AMERICA REQUIRE MANAGEMENT TO EVALUATE TAX POSITIONS TAKEN AND RECOGNIZE A TAX LIABILITY IF THE ORGANIZATION HAS TAKEN AN UNCERTAIN POSITION THAT MORE LIKELY THAN NOT WOULD NOT BE SUSTAINED UPON EXAMINATION BY THE U.S. GOVERNMENT. THE ORGANIZATION HAS ANALYZED THE TAX POSITIONS TAKEN AND HAS CONCLUDED THAT AS OF SEPTEMBER 30, 2022, THERE ARE NO UNCERTAIN POSITIONS TAKEN OR EXPECTED TO BE TAKEN THAT WOULD REQUIRE RECOGNITION OF A LIABILITY OR DISCLOSURE IN THE FINANCIAL STATEMENTS.</ExplanationTxt>
      </SupplementalInformationDetail>
      <SupplementalInformationDetail>
        <FormAndLineReferenceDesc>PART XI, LINE 2D - OTHER ADJUSTMENTS:</FormAndLineReferenceDesc>
        <ExplanationTxt>LOSS ON SALE 4,992.</ExplanationTxt>
      </SupplementalInformationDetail>
      <SupplementalInformationDetail>
        <FormAndLineReferenceDesc>PART XI, LINE 4B - OTHER ADJUSTMENTS:</FormAndLineReferenceDesc>
        <ExplanationTxt>MISCELLANEOUS INCOME 3,446.</ExplanationTxt>
      </SupplementalInformationDetail>
      <SupplementalInformationDetail>
        <FormAndLineReferenceDesc>PART XII, LINE 2D - OTHER ADJUSTMENTS:</FormAndLineReferenceDesc>
        <ExplanationTxt>LOSS ON SALE 4,992.</ExplanationTxt>
      </SupplementalInformationDetail>
      <SupplementalInformationDetail>
        <FormAndLineReferenceDesc>PART XII, LINE 4B - OTHER ADJUSTMENTS:</FormAndLineReferenceDesc>
        <ExplanationTxt>MISCELLANEOUS INCOME 3,446.</ExplanationTxt>
      </SupplementalInformationDetail>
    </IRS990ScheduleD>
    <IRS990ScheduleI documentId="RetDoc1041900001">
      <GrantRecordsMaintainedInd>0</GrantRecordsMaintainedInd>
      <RecipientTable>
        <RecipientBusinessName>
          <BusinessNameLine1Txt>SEAMAR COMMUNITY HEALTH CENTER</BusinessNameLine1Txt>
        </RecipientBusinessName>
        <USAddress>
          <AddressLine1Txt>9635 DES MOINES MEMORIAL</AddressLine1Txt>
          <CityNm>SEATTLE</CityNm>
          <StateAbbreviationCd>WA</StateAbbreviationCd>
          <ZIPCd>98108</ZIPCd>
        </USAddress>
        <RecipientEIN>911020139</RecipientEIN>
        <IRCSectionDesc>501(C)(3)</IRCSectionDesc>
        <CashGrantAmt>108857</CashGrantAmt>
        <NonCashAssistanceAmt>0</NonCashAssistanceAmt>
        <PurposeOfGrantTxt>CHWI HRSA CBW PROJECT</PurposeOfGrantTxt>
      </RecipientTable>
      <RecipientTable>
        <RecipientBusinessName>
          <BusinessNameLine1Txt>THE NEXT DOOR INC</BusinessNameLine1Txt>
        </RecipientBusinessName>
        <USAddress>
          <AddressLine1Txt>965 TUCKER RD</AddressLine1Txt>
          <CityNm>HOOD RIVER</CityNm>
          <StateAbbreviationCd>OR</StateAbbreviationCd>
          <ZIPCd>97031</ZIPCd>
        </USAddress>
        <RecipientEIN>930600421</RecipientEIN>
        <IRCSectionDesc>501(C)(3)</IRCSectionDesc>
        <CashGrantAmt>188434</CashGrantAmt>
        <NonCashAssistanceAmt>0</NonCashAssistanceAmt>
        <PurposeOfGrantTxt>CHWI HRSA CBW PROJECT</PurposeOfGrantTxt>
      </RecipientTable>
      <RecipientTable>
        <RecipientBusinessName>
          <BusinessNameLine1Txt>VIRGINIA GARCIA MEMORIAL HEALTH CENTER</BusinessNameLine1Txt>
        </RecipientBusinessName>
        <USAddress>
          <AddressLine1Txt>PO BOX 6149</AddressLine1Txt>
          <CityNm>ALOHA</CityNm>
          <StateAbbreviationCd>OR</StateAbbreviationCd>
          <ZIPCd>97007</ZIPCd>
        </USAddress>
        <RecipientEIN>930717997</RecipientEIN>
        <IRCSectionDesc>501(C)(3)</IRCSectionDesc>
        <CashGrantAmt>219924</CashGrantAmt>
        <NonCashAssistanceAmt>0</NonCashAssistanceAmt>
        <PurposeOfGrantTxt>CHWI HRSA CBW PROJECT</PurposeOfGrantTxt>
      </RecipientTable>
      <RecipientTable>
        <RecipientBusinessName>
          <BusinessNameLine1Txt>YAKIMA NEIGHBORHOOD HEALTH SERVICE</BusinessNameLine1Txt>
        </RecipientBusinessName>
        <USAddress>
          <AddressLine1Txt>PO BOX 2605</AddressLine1Txt>
          <CityNm>YAKIMA</CityNm>
          <StateAbbreviationCd>WA</StateAbbreviationCd>
          <ZIPCd>98907</ZIPCd>
        </USAddress>
        <RecipientEIN>910928817</RecipientEIN>
        <IRCSectionDesc>501(C)(3)</IRCSectionDesc>
        <CashGrantAmt>175109</CashGrantAmt>
        <NonCashAssistanceAmt>0</NonCashAssistanceAmt>
        <PurposeOfGrantTxt>CHWI HRSA CBW PROJECT</PurposeOfGrantTxt>
      </RecipientTable>
      <RecipientTable>
        <RecipientBusinessName>
          <BusinessNameLine1Txt>UNIVERSITY OF SOUTHERN MISSISSIPPI</BusinessNameLine1Txt>
        </RecipientBusinessName>
        <USAddress>
          <AddressLine1Txt>118 COLLEGE DRIVE BOX 5157</AddressLine1Txt>
          <CityNm>HATTIESBURG</CityNm>
          <StateAbbreviationCd>MS</StateAbbreviationCd>
          <ZIPCd>39406</ZIPCd>
        </USAddress>
        <RecipientEIN>646000818</RecipientEIN>
        <IRCSectionDesc>GOVERNMENT</IRCSectionDesc>
        <CashGrantAmt>17469</CashGrantAmt>
        <NonCashAssistanceAmt>0</NonCashAssistanceAmt>
        <PurposeOfGrantTxt>CHWI CI PROJECT</PurposeOfGrantTxt>
      </RecipientTable>
      <RecipientTable>
        <RecipientBusinessName>
          <BusinessNameLine1Txt>CAMPESINOS SIN FRONTERAS</BusinessNameLine1Txt>
        </RecipientBusinessName>
        <USAddress>
          <AddressLine1Txt>PO BOX 423</AddressLine1Txt>
          <CityNm>SOMERTON</CityNm>
          <StateAbbreviationCd>AZ</StateAbbreviationCd>
          <ZIPCd>85350</ZIPCd>
        </USAddress>
        <RecipientEIN>860944114</RecipientEIN>
        <CashGrantAmt>14986</CashGrantAmt>
        <NonCashAssistanceAmt>0</NonCashAssistanceAmt>
        <PurposeOfGrantTxt>CHWI CI PROJECT</PurposeOfGrantTxt>
      </RecipientTable>
      <RecipientTable>
        <RecipientBusinessName>
          <BusinessNameLine1Txt>COURTYARD MARRIOT CHARLESTON</BusinessNameLine1Txt>
        </RecipientBusinessName>
        <USAddress>
          <AddressLine1Txt>125 CALHOUN ST</AddressLine1Txt>
          <CityNm>CHARLESTON</CityNm>
          <StateAbbreviationCd>SC</StateAbbreviationCd>
          <ZIPCd>29401</ZIPCd>
        </USAddress>
        <RecipientEIN>452185518</RecipientEIN>
        <CashGrantAmt>10803</CashGrantAmt>
        <NonCashAssistanceAmt>0</NonCashAssistanceAmt>
        <PurposeOfGrantTxt>CHWI CI PROJECT</PurposeOfGrantTxt>
      </RecipientTable>
      <RecipientTable>
        <RecipientBusinessName>
          <BusinessNameLine1Txt>MAYFIELD JOHNSON RESOURCES</BusinessNameLine1Txt>
        </RecipientBusinessName>
        <USAddress>
          <AddressLine1Txt>802 SOUTHEAST CIR</AddressLine1Txt>
          <CityNm>HATTIESBURG</CityNm>
          <StateAbbreviationCd>MS</StateAbbreviationCd>
          <ZIPCd>39402</ZIPCd>
        </USAddress>
        <RecipientEIN>853104286</RecipientEIN>
        <CashGrantAmt>12424</CashGrantAmt>
        <NonCashAssistanceAmt>0</NonCashAssistanceAmt>
        <PurposeOfGrantTxt>CHWI CI PROJECT</PurposeOfGrantTxt>
      </RecipientTable>
      <RecipientTable>
        <RecipientBusinessName>
          <BusinessNameLine1Txt>OREGON STATE UNIVERSITY</BusinessNameLine1Txt>
        </RecipientBusinessName>
        <USAddress>
          <AddressLine1Txt>1500 SW JEFFERSON WAY</AddressLine1Txt>
          <CityNm>CORVALLIS</CityNm>
          <StateAbbreviationCd>OR</StateAbbreviationCd>
          <ZIPCd>97339</ZIPCd>
        </USAddress>
        <RecipientEIN>611730890</RecipientEIN>
        <IRCSectionDesc>GOVERNMENT</IRCSectionDesc>
        <CashGrantAmt>48073</CashGrantAmt>
        <NonCashAssistanceAmt>0</NonCashAssistanceAmt>
        <PurposeOfGrantTxt>CHWI CI PROJECT</PurposeOfGrantTxt>
      </RecipientTable>
      <Total501c3OrgCnt>6</Total501c3OrgCnt>
      <TotalOtherOrgCnt>3</TotalOtherOrgCnt>
      <GrantsOtherAsstToIndivInUSGrp>
        <GrantTypeTxt>SCHOLARSHIPS TO ATTEND WESTERN FORUM 22</GrantTypeTxt>
        <RecipientCnt>3</RecipientCnt>
        <CashGrantAmt>2000</CashGrantAmt>
      </GrantsOtherAsstToIndivInUSGrp>
      <GrantsOtherAsstToIndivInUSGrp>
        <GrantTypeTxt>SCHOLARSHIPS TO ATTEND ATSU AND GO ON ROTATIONS</GrantTypeTxt>
        <RecipientCnt>36</RecipientCnt>
        <CashGrantAmt>41115</CashGrantAmt>
      </GrantsOtherAsstToIndivInUSGrp>
      <GrantsOtherAsstToIndivInUSGrp>
        <GrantTypeTxt>CHWI CI PROJECT</GrantTypeTxt>
        <RecipientCnt>13</RecipientCnt>
        <CashGrantAmt>274696</CashGrantAmt>
      </GrantsOtherAsstToIndivInUSGrp>
      <SupplementalInformationDetail>
        <FormAndLineReferenceDesc>PART I, LINE 2:</FormAndLineReferenceDesc>
        <ExplanationTxt>THE ORGANIZATION PROVIDES TRAVEL SCHOLARSHIPS TO INDIVIDUALS AT A FLAT FEE PER PERSON. INDIVIDUALS REGISTER AND APPLY AT THE ANNUAL CONFERENCE. THE ORGANIZATION ALSO PROVIDES STIPENDS TO AT STILL UNIVERSITY STUDENTS FOR TRAVELING AND HOUSING STIPENDS WHEN THEY ARE DOING THEIR TRAINING ROTATIONS AND OCCASIONALLY TO ONE OF OUR LARGER CONFERENCES.</ExplanationTxt>
      </SupplementalInformationDetail>
    </IRS990ScheduleI>
    <IRS990ScheduleJ documentId="RetDoc1042400001">
      <CompensationSurveyInd>X</CompensationSurveyInd>
      <BoardOrCommitteeApprovalInd>X</BoardOrCommitteeApprovalInd>
      <SeverancePaymentInd>0</SeverancePaymentInd>
      <SupplementalNonqualRtrPlanInd>0</SupplementalNonqualRtrPlanInd>
      <EquityBasedCompArrngmInd>0</EquityBasedCompArrngmInd>
      <CompBasedOnRevenueOfFlngOrgInd>0</CompBasedOnRevenueOfFlngOrgInd>
      <CompBsdOnRevRelatedOrgsInd>0</CompBsdOnRevRelatedOrgsInd>
      <CompBsdNetEarnsFlngOrgInd>0</CompBsdNetEarnsFlngOrgInd>
      <CompBsdNetEarnsRltdOrgsInd>0</CompBsdNetEarnsRltdOrgsInd>
      <AnyNonFixedPaymentsInd>1</AnyNonFixedPaymentsInd>
      <InitialContractExceptionInd>0</InitialContractExceptionInd>
      <RltdOrgOfficerTrstKeyEmplGrp>
        <PersonNm>BRUCE GRAY</PersonNm>
        <TitleTxt>CEO</TitleTxt>
        <BaseCompensationFilingOrgAmt>215714</BaseCompensationFilingOrgAmt>
        <CompensationBasedOnRltdOrgsAmt>0</CompensationBasedOnRltdOrgsAmt>
        <BonusFilingOrganizationAmount>1624</BonusFilingOrganizationAmount>
        <BonusRelatedOrganizationsAmt>0</BonusRelatedOrganizationsAmt>
        <OtherCompensationFilingOrgAmt>0</OtherCompensationFilingOrgAmt>
        <OtherCompensationRltdOrgsAmt>0</OtherCompensationRltdOrgsAmt>
        <DeferredCompensationFlngOrgAmt>1300</DeferredCompensationFlngOrgAmt>
        <DeferredCompRltdOrgsAmt>0</DeferredCompRltdOrgsAmt>
        <NontaxableBenefitsFilingOrgAmt>15929</NontaxableBenefitsFilingOrgAmt>
        <NontaxableBenefitsRltdOrgsAmt>0</NontaxableBenefitsRltdOrgsAmt>
        <TotalCompensationFilingOrgAmt>234567</TotalCompensationFilingOrgAmt>
        <TotalCompensationRltdOrgsAmt>0</TotalCompensationRltdOrgsAmt>
        <CompReportPrior990FilingOrgAmt>0</CompReportPrior990FilingOrgAmt>
        <CompReportPrior990RltdOrgsAmt>0</CompReportPrior990RltdOrgsAmt>
      </RltdOrgOfficerTrstKeyEmplGrp>
      <SupplementalInformationDetail>
        <FormAndLineReferenceDesc>PART I, LINE 7</FormAndLineReferenceDesc>
        <ExplanationTxt>MANAGEMENT AND THE BOARD DETERMINES DISCRETIONARY BONUSES BASED UPON THE ORGANIZATIONS BUDGET, YEARS WORKED AND BIRTHDAY AWARDS.</ExplanationTxt>
      </SupplementalInformationDetail>
    </IRS990ScheduleJ>
    <IRS990ScheduleO documentId="RetDoc1044400001">
      <SupplementalInformationDetail>
        <FormAndLineReferenceDesc>FORM 990, PART III, LINE 3</FormAndLineReferenceDesc>
        <ExplanationTxt>THE ORGANIZATION WENT BACK TO IN-PERSON CONFERENCES RATHER THAN ENTIRELY VIRTUAL AT WESTERN FORUM IN APRIL 2022.</ExplanationTxt>
      </SupplementalInformationDetail>
      <SupplementalInformationDetail>
        <FormAndLineReferenceDesc>FORM 990, PART VI, SECTION A, LINE 1A</FormAndLineReferenceDesc>
        <ExplanationTxt>THE GOVERNING BODY DELEGATES BROAD AUTHORITY TO THE EXECUTIVE COMMITTEE. THE NWRPCA BOARD HAS FOUR ELECTED OFFICERS: PRESIDENT, PRESIDENT-ELECT, TREASURER AND SECRETARY. THE EXECUTIVE COMMITTEE CONSISTS OF THE FOUR OFFICERS, THE IMMEDIATE PAST PRESIDENT, AND THREE MEMBERS AT LARGE ELECTED BY AND FROM THE BOARD OF DIRECTORS. BY CONVENTION, AT LEAST ONE MEMBER OF THE EXECUTIVE COMMITEE IS A CLINICIAN. ACCORDING TO THE BYLAWS, THE TERM FOR OFFICERS AND EXECUTIVE COMMITTEE MEMBERS IS ONE YEAR. BY CONVENTION, THE PRESIDENT AND PRESIDENT-ELECT SERVE TWO CONSECUTIVE TEAMS. THE EXECUTIVE COMMITTEE HAS THE AUTHORITY TO ACT ON BEHALF OF THE BOARD IN ALL BUT A HANDFUL OF MATTERS. THE EXECUTIVE COMMITTEE MEETS MONTHLY BY CONFERENCE CALL. THE QUORUM FOR MEETINGS IS A MAJORITY OF MEMEBERS. THE EXECUTIVE COMMITTEE HAS AND MAY EXERCISE ALL OF THE AUTHORITY OF THE BOARD OF DIRECTORS IN THE MANAGEMENT OF THE ORGANIZATION, EXCEPT FOR THOSE ITEMS LISTED IN THE BYLAWS AS NOT UNDER THE AUTHORITY OF THE EXECUTIVE COMMITTEE.</ExplanationTxt>
      </SupplementalInformationDetail>
      <SupplementalInformationDetail>
        <FormAndLineReferenceDesc>FORM 990, PART VI, SECTION A, LINE 6</FormAndLineReferenceDesc>
        <ExplanationTxt>MEMBERSHIP IN NORTHWEST REGIONAL PRIMARY CARE ASSOCIATION IS DIVIDED INTO FOUR CATEGORIES: -CATEGORY A MEMBERS MUST BE A NON-PROFIT CORPORATIONS EXEMPT UNDER SECTION 501(C)(3) OF THE U.S. INTERNAL REVENUE CODE, OR PUBLIC CORPORATIONS AND MEET THE ORGANIZATIONAL AND OPERATIONAL REQUIREMENTS FOR FUNDING UNDER SECTION 330 OF THE U.S PUBLIC HEALTH SERVICE. -CATEGORY B MEMBERS MUST BE NON-PROFIT CORPORATIONS EXEMPT UNDER SECTION 501(C)(3) OF THE U.S. INTERNAL REVENUE CODE, OR PUBLIC CORPORATIONS AND AS JUDGED BY PROTOCOL APPROVED BY THE BOARD OF DIRECTORS, PROVIDE COMPREHENSIVE PRIMARY HEALTH CARE SERVICES WITH A SPECIFIC MISSION TO SERVICE LOW-INCOME PERSONS. -CATEGORY C MEMBERS MUST BE INDIVIDUALS AFFILIATED WITH NWRPCS MEMBER ORGANIZATIONS, OR AFFILIATED WITH ORGANIZATIONS THAT ARE ENGAGED IN COLLABORATION AND PARTNERSHIP WITH NWPCA AND/OR THAT HAVE A SIMILAR MISSION, GOALS OR OBJECTIVES. -CATEGORY D MEMBERS MUST BE ORGANIZATIONS OR INSTITUTIONS THAT ARE ENGAGED IN COLLABORATION AND PARTNERSHIP WITH NWRPCA AND AS JUDGED BY A PROTOCOL APPROVED BY THE BOARD OF DIRECTORS, HAVE A SIMILAR MISSION, GOALS, AND OBJECTIVES.</ExplanationTxt>
      </SupplementalInformationDetail>
      <SupplementalInformationDetail>
        <FormAndLineReferenceDesc>FORM 990, PART VI, SECTION A, LINE 7A</FormAndLineReferenceDesc>
        <ExplanationTxt>THE DIRECTORS ARE ELECTED BY AND FROM THE ELIGIBLE CATEGORY A MEMBERSHIP OF THAT STATE AND ARE CONFIRMED BY THE GENERAL MEMBERSHIP AT THE ANNUAL MEMBERSHIP MEETING.</ExplanationTxt>
      </SupplementalInformationDetail>
      <SupplementalInformationDetail>
        <FormAndLineReferenceDesc>FORM 990, PART VI, SECTION A, LINE 7B</FormAndLineReferenceDesc>
        <ExplanationTxt>THE AUTHORITY TO AMEND THE ARTICLES OF INCORPORATION OR BYLAWS IS VESTED IN THE CATEGORY A MEMBERS OF THE ORGANIZATION.</ExplanationTxt>
      </SupplementalInformationDetail>
      <SupplementalInformationDetail>
        <FormAndLineReferenceDesc>FORM 990, PART VI, SECTION B, LINE 11B</FormAndLineReferenceDesc>
        <ExplanationTxt>THE RETURN WILL BE PRESENTED TO THE FULL BOARD FOR APPROVAL AT THE FIRST BOARD MEETING FOLLOWING COMPLETION OF THE DRAFT. THE BOARD PACKET IS GENERALLY SENT OUT SEVERAL DAYS BEFORE THE BOARD MEETING SO THAT THE BOARD HAS TIME TO RETURN AND FORMULATE QUESTIONS.</ExplanationTxt>
      </SupplementalInformationDetail>
      <SupplementalInformationDetail>
        <FormAndLineReferenceDesc>FORM 990, PART VI, SECTION B, LINE 12C</FormAndLineReferenceDesc>
        <ExplanationTxt>BOARD MEMBERS REVIEW AND SIGN CONFLICT OF INTEREST STATEMENTS ANNUALLY. THE COMPLIANCE OFFICER REVIEWS THE ENTIRE COMPLIANCE PLAN, INCLUDING THE CONFLICT OF INTEREST POLICY AND ADHERENCE THERETO ANNUALLY.</ExplanationTxt>
      </SupplementalInformationDetail>
      <SupplementalInformationDetail>
        <FormAndLineReferenceDesc>FORM 990, PART VI, SECTION B, LINE 15</FormAndLineReferenceDesc>
        <ExplanationTxt>FORM 990, PART VI, LINE 15A - COMPENSATION PROCESS FOR TOP OFFICIAL THE BOARD REVIEWS THE CEO'S COMPENSATION ANNUALLY, UTILIZING A PCA SALARY SURVEY CONDUCTED BY NACGC/HRSA; A SALARY FROM ARCHBRIGHT OF CEOS IN SEATTLE AREA NON-PROFITS, AND INTERNAL SALARY DATA. FORM 990, PART VI, LINE 15B - COMPENSATION PROCESS FOR OFFICERS NWRPCA COMMISSIONS ARCHBRIGHT TO CONDUCT A BIENNIAL SALARY SURVEY FOR ALL STAFF POSITIONS.</ExplanationTxt>
      </SupplementalInformationDetail>
      <SupplementalInformationDetail>
        <FormAndLineReferenceDesc>FORM 990, PART VI, SECTION C, LINE 19</FormAndLineReferenceDesc>
        <ExplanationTxt>THE ORGANIZATION MAKES ITS GOVERNING DOCUMENTS, CONFLICT OF INTEREST POLICY AND FINANCIAL STATEMENTS UPON REQUEST.</ExplanationTxt>
      </SupplementalInformationDetail>
      <SupplementalInformationDetail>
        <FormAndLineReferenceDesc>FORM 990, PART IX, LINE 11G</FormAndLineReferenceDesc>
        <ExplanationTxt>PROFESSIONAL FEES AND HONORARIA : PROGRAM SERVICE EXPENSES 296,454. MANAGEMENT AND GENERAL EXPENSES 152,221. FUNDRAISING EXPENSES 8,708. TOTAL EXPENSES 457,383.</ExplanationTxt>
      </SupplementalInformationDetail>
    </IRS990ScheduleO>
  </ReturnData>
</Return>
